Workbook

Sheet Portada
A2: RFP — Request for Proposal
A3: Transformación Digital — Inversora de Capilla S.A.
A4: OpenSource Consulting · Grupo 3 · FCE-UBA · 2026
A6: Empresa solicitante | B6: Inversora de Capilla S.A.
A7: Consultora | B7: OpenSource Consulting
A8: Responsable sponsor | B8: Ramiro Illa y socio
A9: Fecha de emisión | B9: Junio, 2026
A10: Versión | B10: v4
A11: Ponderación global | B11: Funcional 45% | Técnico 15% | Económico 20% | Proveedor 20%

Sheet Introducción
A2: Metodología adoptada | B2: TOGAF ADM | D2: Supuestos de evaluación
B3: Modelo de Innovación de Doblin | D3: Horizonte de evaluación: 3 años.
D4: Cantidad estimada: 5-15 usuarios.
D5: Modelo SaaS Cloud First.
A6: Matriz de ponderación | D6: Operación Argentina.
B8: Dimensión del RFP | C8: Ponderación | D8: Foco Crítico de Evaluación
B10: Aspecto Funcional | C10: 0.45 | D10: Capacidad de cobertura del CRM comercial, embudo de ventas, repositorio documental unificado, automatización financiera y módulos de control de obra en campo.
B11: Aspecto Técnico | C11: 0.15 | D11: Cumplimiento del modelo 100% SaaS nube, APIs de integración abierta, seguridad avanzada (MFA, RBAC), cifrado de datos (Ley 25.326) y disponibilidad del 99.5% uptime.
B12: Aspecto Económico | C12: 0.2 | D12: Análisis del Costo Total de Propiedad (TCO) proyectado a 3 años, diferenciando claramente la inversión inicial (CAPEX) del costo operativo mensual de las suscripciones (OPEX).
B13: Aspecto Proveedor | C13: 0.2 | D13: Idoneidad y experiencia en los sectores de Real Estate / PropTech, solidez legal y fiscal en Argentina (facturación ARS / AFIP) y planes estructurados de soporte con penalidades.
A16: Escalas | B16: NAT. | C16: - Lo tiene de manera nativa | D16: 1
B17: INC. | C17: - No lo tiene pero nos lo incluye si lo compramos | D17: 0.75
B18: CONF. | C18: - No lo tiene pero es configurable (cotizable) | D18: 0.5
B19: DES. | C19: - No lo tiene pero lo puede desarrollar | D19: 0.25
B20: N/A | C20: - No lo tiene / ni lo puede desarrollar | D20: 0
B22: — NOTA ACLARATORIA SOBRE USO DE ESCALAS —
B23: Aspectos Funcional y Técnico
B24: Las escalas NAT/INC/CONF/DES/N/A evalúan si la plataforma posee la funcionalidad o el atributo técnico de forma nativa, si puede incluirlo con adquisición de módulo adicional, si es configurable, si debe desarrollarse a medida o si directamente no lo ofrece ni puede ofrecerlo.
B26: Aspecto Económico — Escala adaptada
B27: Puntaje | C27: Descripción | D27: Ejemplos : | E27: Coste Total de Propiedad (TCO) a 3 años
B28: 1 | C28: Muy competitivo | E28: Puntaje | F28: TCO
B29: 0.75 | C29: Competitivo | E29: 1 | F29: ≤ USD 10.000
B30: 0.5 | C30: Aceptable | E30: 0.75 | F30: USD 10.001–15.000
B31: 0.25 | C31: Elevado | E31: 0.5 | F31: USD 15.001–20.000
B32: 0 | C32: Inviable | E32: 0.25 | F32: USD 20.001–25.000
E33: 0 | F33: > USD 25.000
B34: Certificaciones
B35: Puntaje | C35: Condición | E35: Licencias
B36: 0 | C36: Sin certificaciones | E36: Puntaje | F36: Licencia mensual
B37: 0.5 | C37: ISO 27001 o equivalente | E37: 1 | F37: ≤ USD 50 por usuario
B38: 1 | C38: ISO 27001 + SOC 2 + otras certificaciones relevantes | E38: 0.75 | F38: USD 51–75
E39: 0.5 | F39: USD 76–100
B40: Experiencia en la Industria | E40: 0.25 | F40: USD 101–150
B41: (Aplica a experiencia inmobiliaria, construcción, PyMEs similares) | E41: 0 | F41: > USD 150
B42: Cumplimiento | C42: Criterio
B43: 1 | C43: Más de 10 casos comprobables en la industria o segmento
B44: 0.75 | C44: Entre 5 y 10 casos
B45: 0.5 | C45: Entre 2 y 4 casos
B46: 0.25 | C46: 1 caso documentado
B47: 0 | C47: Sin referencias relevantes
B49: Trayectoria y Solidez del Proveedor
B50: (Aplica a antigüedad, clientes, presencia internacional, estabilidad financiera)
B51: Cumplimiento | C51: Criterio
B52: 1 | C52: >15 años en el mercado y presencia internacional consolidada
B53: 0.75 | C53: 10-15 años y presencia regional
B54: 0.5 | C54: 5-10 años y presencia nacional
B55: 0.25 | C55: <5 años o presencia limitada
B56: 0 | C56: Sin evidencia suficiente
B58: Soporte y Servicio
B59: (Aplica a soporte en español, SLA, canales de atención)
B60: Cumplimiento | C60: Criterio
B61: 1 | C61: Soporte en español, múltiples canales, SLA formal 24x7
B62: 0.75 | C62: Soporte en español con SLA en horario extendido
B63: 0.5 | C63: Soporte en español sin SLA formal
B64: 0.25 | C64: Soporte principalmente en inglés
B65: 0 | C65: Sin soporte verificable
B67: Referencias y Satisfacción de Clientes
B68: (Aplica a casos de éxito, testimonios, reputación)
B69: Cumplimiento | C69: Criterio
B70: 1 | C70: Referencias verificables y alta satisfacción documentada
B71: 0.75 | C71: Varias referencias positivas
B72: 0.5 | C72: Algunas referencias positivas
B73: 0.25 | C73: Pocas referencias disponibles
B74: 0 | C74: Sin referencias
B76: Capacitación y Adopción
B77: (Aplica a onboarding, formación, documentación)
B78: Cumplimiento | C78: Criterio
B79: 1 | C79: Capacitación estructurada + documentación + academia
B80: 0.75 | C80: Capacitación y documentación formal
B81: 0.5 | C81: Documentación suficiente
B82: 0.25 | C82: Documentación básica
B83: 0 | C83: Sin recursos disponibles

Sheet Matriz Funcional
B2: ASPECTO FUNCIONAL | C2: Ponderación | D2: Peso relativo | E2: Detalle | F2: Comentarios | G2: Justificación | H2: MS Dynamics 365 | K2: Zoho One
C3: 0.45 | H3: Puntaje | I3: Puntaje Ponderado | J3: Aporte Relativo | K3: Puntaje | L3: Puntaje Ponderado | M3: Aporte Relativo
B4: A. CRM — Gestión de Relaciones con el Cliente | C4: 0.4 | D4: =C3*C4 -> 0.18 | I4: =SUM(I5+I9+I14+I18)*C4 -> 0.39 | J4: =SUM(J5+J9+J14+J18) -> 0.1755 | L4: =SUM(L5+L9+L14+L18)*C4 -> 0.39 | M4: =SUM(M5+M9+M14+M18) -> 0.1755
B5: 1. Gestión de Contactos y Cuentas | C5: 0.2 | D5: =C3*C4*C5 -> 0.036 | I5: =SUM(I6:I8)*C5 -> 0.2 | J5: =SUM(J6:J8) -> 0.036 | L5: =SUM(L6:L8)*C5 -> 0.2 | M5: =SUM(M6:M8) -> 0.036
B6: 1.1 Ficha 360° del cliente | C6: 0.4 | D6: =0.45*C4*C5*C6 -> 0.0144 | E6: Vista unificada del cliente: datos personales, propiedades de interés, operaciones realizadas e historial completo. | F6: Inversora de Capilla no tiene hoy un perfil unificado de cliente; la info está en WhatsApp, papel y planillas. | G6: Base del CRM: sin ficha 360° no existe trazabilidad comercial ni operativa. | H6: 1 | I6: =H6*C6 -> 0.4 | J6: =I6*D5 -> 0.0144 | K6: 1 | L6: =K6*C6 -> 0.4 | M6: =L6*D5 -> 0.0144
B7: 1.2 Segmentación de clientes | C7: 0.3 | D7: =0.45*C4*C5*C7 -> 0.0108 | E7: Capacidad de crear segmentos y listas dinámicas por criterios: zona, tipo de propiedad, estado del ciclo, perfil inversor. | F7: Permite personalizar campañas y priorizar el seguimiento según el perfil del comprador. | G7: La segmentación es prerequisito de toda estrategia de marketing y retención. | H7: 1 | I7: =H7*C7 -> 0.3 | J7: =I7*D5 -> 0.0108 | K7: 1 | L7: =K7*C7 -> 0.3 | M7: =L7*D5 -> 0.0108
B8: 1.3 Historial completo y trazabilidad | C8: 0.3 | D8: =0.45*C4*C5*C8 -> 0.0108 | E8: Registro cronológico de todas las interacciones: llamadas, reuniones, mails, visitas a obra y documentación compartida. | H8: 1 | I8: =H8*C8 -> 0.3 | J8: =I8*D5 -> 0.0108 | K8: 1 | L8: =K8*C8 -> 0.3 | M8: =L8*D5 -> 0.0108
B9: 2. Gestión Comercial y Pipeline | C9: 0.3 | D9: =C3*C4*C9 -> 0.054 | I9: =SUM(I10:I13)*C9 -> 0.3 | J9: =SUM(J10:J13) -> 0.054 | L9: =SUM(L10:L13)*C9 -> 0.3 | M9: =SUM(M10:M13) -> 0.054
B10: 2.1 CRM centralizado (leads, oportunidades, cuentas) | C10: 0.3 | D10: =0.45*C4*C9*C10 -> 0.0162 | E10: Gestión de leads entrantes, conversión a oportunidades y seguimiento de cuentas activas desde una plataforma única. | F10: Reemplaza el seguimiento disperso en WhatsApp y 6 planillas Excel. | G10: Núcleo del CRM — sin esta funcionalidad no existe transformación comercial. | H10: 1 | I10: =H10*C10 -> 0.3 | J10: =I10*D9 -> 0.0162 | K10: 1 | L10: =K10*C10 -> 0.3 | M10: =L10*D9 -> 0.0162
B11: 2.2 Pipeline de ventas con etapas y probabilidad de cierre | C11: 0.25 | D11: =0.45*C4*C9*C11 -> 0.0135 | E11: Embudo comercial configurable: etapas, propietarios, fechas estimadas y probabilidad de conversión por oportunidad. | H11: 1 | I11: =H11*C11 -> 0.25 | J11: =I11*D9 -> 0.0135 | K11: 1 | L11: =K11*C11 -> 0.25 | M11: =L11*D9 -> 0.0135
B12: 2.3 Lead scoring y calificación automática | C12: 0.2 | D12: =0.45*C4*C9*C12 -> 0.0108 | E12: Puntuación automática de leads según comportamiento, origen, perfil y engagement para priorizar el equipo de ventas. | F12: Con 40-70 leads potenciales simultáneos, la priorización manual genera pérdida de oportunidades. | G12: Maximiza el ROI del equipo comercial reduciendo el tiempo dedicado a leads no calificados. | H12: 1 | I12: =H12*C12 -> 0.2 | J12: =I12*D9 -> 0.0108 | K12: 1 | L12: =K12*C12 -> 0.2 | M12: =L12*D9 -> 0.0108
B13: 2.4 Automatización de workflows comerciales | C13: 0.25 | D13: =0.45*C4*C9*C13 -> 0.0135 | E13: Reglas automáticas: asignación de leads, envío de recordatorios, creación de tareas y actualización de estados sin intervención manual. | F13: Actualmente cada paso comercial requiere acción manual, generando omisiones y desvíos. | G13: Componente clave de la automatización comercial — reduce carga sobre el equipo de ventas. | H13: 1 | I13: =H13*C13 -> 0.25 | J13: =I13*D9 -> 0.0135 | K13: 1 | L13: =K13*C13 -> 0.25 | M13: =L13*D9 -> 0.0135
B14: 3. Marketing y Campañas | C14: 0.25 | D14: =C3*C4*C14 -> 0.045 | I14: =SUM(I15:I17)*C14 -> 0.25 | J14: =SUM(J15:J17) -> 0.045 | L14: =SUM(L15:L17)*C14 -> 0.25 | M14: =SUM(M15:M17) -> 0.045
B15: 3.1 Segmentación y listas dinámicas para campañas | C15: 0.35 | D15: =0.45*C4*C14*C15 -> 0.01575 | E15: Definición de audiencias dinámicas para campañas basadas en atributos del CRM (zona, estado, interés, historial). | F15: Permite comunicar la oferta correcta al cliente correcto en el momento adecuado. | G15: Sin segmentación dinámica, las campañas pierden precisión y generan fatiga en los contactos. | H15: 1 | I15: =H15*C15 -> 0.35 | J15: =I15*D14 -> 0.01575 | K15: 1 | L15: =K15*C15 -> 0.35 | M15: =L15*D14 -> 0.01575
B16: 3.2 Campañas masivas multi-canal (email / WhatsApp) | C16: 0.4 | D16: =0.45*C4*C14*C16 -> 0.018 | E16: Ejecución de campañas de comunicación masiva desde el CRM hacia los canales preferidos del cliente. | F16: Hoy la comunicación es manual, uno a uno, por WhatsApp personal de cada vendedor. | G16: Escala el alcance comercial sin escalar la estructura de personal. | H16: 1 | I16: =H16*C16 -> 0.4 | J16: =I16*D14 -> 0.018 | K16: 1 | L16: =K16*C16 -> 0.4 | M16: =L16*D14 -> 0.018
B17: 3.3 Trazabilidad multicanal del cliente | C17: 0.25 | D17: =0.45*C4*C14*C17 -> 0.01125 | E17: Registro unificado de interacciones por email, WhatsApp, llamadas y visitas en el perfil del cliente. | H17: 1 | I17: =H17*C17 -> 0.25 | J17: =I17*D14 -> 0.01125 | K17: 1 | L17: =K17*C17 -> 0.25 | M17: =L17*D14 -> 0.01125
B18: 4. Postventa y Fidelización | C18: 0.25 | D18: =C3*C4*C18 -> 0.045 | I18: =SUM(I19:I20)*C18 -> 0.225 | J18: =SUM(J19+J20) -> 0.0405 | L18: =SUM(L19:L20)*C18 -> 0.225 | M18: =SUM(M19:M20) -> 0.0405
B19: 4.1 Gestión postventa y satisfacción del cliente | C19: 0.6 | D19: =0.45*C4*C18*C19 -> 0.027 | E19: Seguimiento de compradores post-entrega: relevamiento de satisfacción, gestión de reclamos y alertas de vencimientos. | H19: 1 | I19: =H19*C19 -> 0.6 | J19: =I19*D18 -> 0.027 | K19: 1 | L19: =K19*C19 -> 0.6 | M19: =L19*D18 -> 0.027
B20: 4.2 Portal o historial de servicio post-entrega | C20: 0.4 | D20: =0.45*C4*C18*C20 -> 0.018 | E20: Acceso del cliente a documentación, comprobantes, estado de obra y comunicaciones históricas. | F20: Reduce consultas recurrentes al equipo y mejora la percepción de transparencia. | G20: Diferenciador de propuesta de valor para un mercado donde la confianza es clave. | H20: 0.75 | I20: =H20*C20 -> 0.3 | J20: =I20*D18 -> 0.0135 | K20: 0.75 | L20: =K20*C20 -> 0.3 | M20: =L20*D18 -> 0.0135
B21: B. BI — Business Intelligence | C21: 0.2 | D21: =0.45*C21 -> 0.09 | I21: =SUM(I22+I25+I29+I32)*C21 -> 0.2 | J21: =SUM(J22+J25+J29+J32) -> 0.09 | L21: =SUM(L22+L25+L29+L32)*C21 -> 0.177 | M21: =SUM(M22+M25+M29+M32) -> 0.07965
B22: 5. Integración de Datos y Repositorio Analítico | C22: 0.2 | D22: =0.45*C21*C22 -> 0.018 | I22: =SUM(I23:I24)*C22 -> 0.2 | J22: =SUM(J23+J23) -> 0.018 | L22: =SUM(L23:L24)*C22 -> 0.175 | M22: =SUM(M23+M24) -> 0.01575
B23: 5.1 ETL / Conectores nativos desde CRM, proyectos y finanzas | C23: 0.5 | D23: =0.45*C21*C22*C23 -> 0.009 | E23: Capacidad de extraer, transformar y cargar datos desde los módulos operativos al repositorio analítico sin intervención manual. | F23: Sin ETL, el BI requiere exportaciones manuales periódicas desde las planillas. | G23: Prerequisito técnico para cualquier análisis actualizado y confiable. | H23: 1 | I23: =H23*C23 -> 0.5 | J23: =I23*D22 -> 0.009 | K23: 1 | L23: =K23*C23 -> 0.5 | M23: =L23*D22 -> 0.009
B24: 5.2 Repositorio analítico unificado (data mart / DWH básico) | C24: 0.5 | D24: =0.45*C21*C22*C24 -> 0.009 | E24: Modelo de datos histórico y consistente que centraliza métricas de ventas, costos, proyectos y clientes para análisis. | F24: Un repositorio unificado elimina la contradicción de datos entre áreas. | G24: Fundamento del análisis multidimensional y la toma de decisiones basada en datos. | H24: 1 | I24: =H24*C24 -> 0.5 | J24: =I24*D22 -> 0.009 | K24: 0.75 | L24: =K24*C24 -> 0.375 | M24: =L24*D22 -> 0.00675
B25: 6. Análisis, Visualización e Indicadores | C25: 0.4 | D25: =0.45*C21*C25 -> 0.036 | I25: =SUM(I26:I28)*C25 -> 0.4 | J25: =SUM(J26:J28) -> 0.036 | L25: =SUM(L26:L28)*C25 -> 0.335 | M25: =SUM(M26:M28) -> 0.03015
B26: 6.1 Dashboards ejecutivos con KPIs configurables | C26: 0.4 | D26: =0.45*C21*C25*C26 -> 0.0144 | E26: Paneles interactivos con indicadores clave: ventas, rentabilidad por proyecto, avance de obra y flujo de caja en tiempo real. | F26: Hoy las decisiones se toman sin datos consolidados; los directivos no tienen visibilidad unificada. | G26: Impacto directo en calidad de decisiones estratégicas. | H26: 1 | I26: =H26*C26 -> 0.4 | J26: =I26*D25 -> 0.0144 | K26: 0.75 | L26: =K26*C26 -> 0.3 | M26: =L26*D25 -> 0.0108
B27: 6.2 Reportes estándar y personalizados por área | C27: 0.35 | D27: =0.45*C21*C25*C27 -> 0.0126 | E27: Generación de informes por área (comercial, financiero, obra) con filtros, exportación y programación de envío. | F27: Elimina el armado manual de reportes en Excel que hoy consume horas semanales del equipo. | G27: Libera tiempo operativo y mejora la exactitud de la información reportada. | H27: 1 | I27: =H27*C27 -> 0.35 | J27: =I27*D25 -> 0.0126 | K27: 1 | L27: =K27*C27 -> 0.35 | M27: =L27*D25 -> 0.0126
B28: 6.3 Análisis ad-hoc y drill-down por dimensión | C28: 0.25 | D28: =0.45*C21*C25*C28 -> 0.009 | E28: Capacidad del usuario de explorar datos dinámicamente (por zona, período, proyecto, vendedor) sin depender de IT. | F28: Permite responder preguntas no planificadas ante situaciones concretas de negocio. | G28: Autoservicio analítico — requisito de madurez básico para una empresa en transformación. | H28: 1 | I28: =H28*C28 -> 0.25 | J28: =I28*D25 -> 0.009 | K28: 0.75 | L28: =K28*C28 -> 0.1875 | M28: =L28*D25 -> 0.00675
B29: 7. Alertas y Proyecciones | C29: 0.25 | D29: =0.45*C21*C29 -> 0.0225 | I29: =SUM(I30:I31)*C29 -> 0.25 | J29: =SUM(J30:J31) -> 0.0225 | L29: =SUM(L30:L31)*C29 -> 0.225 | M29: =SUM(M30:M31) -> 0.02025
B30: 7.1 Alertas automáticas ante desvíos de KPIs | C30: 0.6 | D30: =0.45*C21*C29*C30 -> 0.0135 | E30: Notificaciones proactivas cuando indicadores superan umbrales: retraso de obra, caída de conversión, déficit de caja. | F30: Elimina el control manual con planillas estáticas que detectan problemas tarde. | G30: Control preventivo — reduce impacto de desvíos al identificarlos tempranamente. | H30: 1 | I30: =H30*C30 -> 0.6 | J30: =I30*D29 -> 0.0135 | K30: 1 | L30: =K30*C30 -> 0.6 | M30: =L30*D29 -> 0.0135
B31: 7.2 Forecasting y proyecciones básicas de ventas/costos | C31: 0.4 | D31: =0.45*C21*C29*C31 -> 0.009 | E31: Proyecciones automáticas de ventas, costos y rentabilidad basadas en el historial y el pipeline actual. | F31: Inversora de Capilla toma decisiones de inversión sin proyecciones formales. | G31: Crítico para la planificación financiera y la gestión de riesgo de proyectos. | H31: 1 | I31: =H31*C31 -> 0.4 | J31: =I31*D29 -> 0.009 | K31: 0.75 | L31: =K31*C31 -> 0.3 | M31: =L31*D29 -> 0.00675
B32: 8. Distribución y Acceso | C32: 0.15 | D32: =0.45*C21*C32 -> 0.0135 | I32: =SUM(I33:I34)*C32 -> 0.15 | J32: =SUM(J33:J34) -> 0.0135 | L32: =SUM(L33:L34)*C32 -> 0.15 | M32: =SUM(M33:M34) -> 0.0135
B33: 8.1 Acceso móvil a dashboards y reportes | C33: 0.6 | D33: =0.45*C21*C32*C33 -> 0.0081 | E33: Visualización y navegación de indicadores desde smartphones y tablets. | F33: Los directivos operan desde Los Cardales — el acceso móvil es requisito operativo. | G33: Alineado con el requisito cloud-first y la gestión remota. | H33: 1 | I33: =H33*C33 -> 0.6 | J33: =I33*D32 -> 0.0081 | K33: 1 | L33: =K33*C33 -> 0.6 | M33: =L33*D32 -> 0.0081
B34: 8.2 Exportación y distribución programada de informes | C34: 0.4 | D34: =0.45*C21*C32*C34 -> 0.0054 | E34: Envío automático de reportes por email a frecuencias configurables (semanal, mensual). | F34: Garantiza que los directivos reciban información sin tener que acceder activamente al sistema. | G34: Mejora la adopción del BI al llevar los datos a donde ya trabaja el equipo. | H34: 1 | I34: =H34*C34 -> 0.4 | J34: =I34*D32 -> 0.0054 | K34: 1 | L34: =K34*C34 -> 0.4 | M34: =L34*D32 -> 0.0054
B35: C. MDM — Gestión de Datos Maestros | C35: 0.1 | D35: =0.45*C35 -> 0.045 | I35: =SUM(I36+I40)*C35 -> 0.0925 | J35: =SUM(J36+J40) -> 0.041625 | L35: =SUM(L36+L40)*C35 -> 0.075 | M35: =SUM(M36+M40) -> 0.03375
B36: 9. Repositorio Único de Entidades | C36: 0.5 | D36: =0.45*C35*C36 -> 0.0225 | I36: =SUM(I37:I39)*C36 -> 0.425 | J36: =SUM(J37:J39) -> 0.019125 | L36: =SUM(L37:L39)*C36 -> 0.375 | M36: =SUM(M37:M39) -> 0.016875
B37: 9.1 Golden record del cliente (entidad única) | C37: 0.4 | D37: =0.45*C35*C36*C37 -> 0.009 | E37: Registro único, deduplicado y autoritativo de cada cliente, usado por todos los módulos del sistema. | F37: Hoy la misma persona puede existir en múltiples planillas con datos inconsistentes. | G37: Es la condición para que el CRM, BI y Finanzas hablen del mismo cliente. | H37: 1 | I37: =H37*C37 -> 0.4 | J37: =I37*D36 -> 0.009 | K37: 0.75 | L37: =K37*C37 -> 0.3 | M37: =L37*D36 -> 0.00675
B38: 9.2 Maestro de proyectos y propiedades | C38: 0.3 | D38: =0.45*C35*C36*C38 -> 0.00675 | E38: Catálogo único de proyectos, unidades y propiedades con sus atributos, estados y referencias cruzadas. | F38: Sin un maestro único, los mismos proyectos tienen datos distintos en CRM, obra y finanzas. | G38: Prerequisito para la gestión integrada del ciclo del proyecto inmobiliario. | H38: 0.75 | I38: =H38*C38 -> 0.225 | J38: =I38*D36 -> 0.0050625 | K38: 0.75 | L38: =K38*C38 -> 0.225 | M38: =L38*D36 -> 0.0050625
B39: 9.3 Maestro de contratistas y proveedores | C39: 0.3 | D39: =0.45*C35*C36*C39 -> 0.00675 | E39: Registro centralizado de contratistas y proveedores con datos de contacto, categoría, historial y habilitaciones. | F39: Hoy hay 40-70 contratistas sin un registro formal ni estandarizado. | G39: Permite gestionar contratos, pagos y seguimiento de obra desde una fuente única. | H39: 0.75 | I39: =H39*C39 -> 0.225 | J39: =I39*D36 -> 0.0050625 | K39: 0.75 | L39: =K39*C39 -> 0.225 | M39: =L39*D36 -> 0.0050625
B40: 10. Calidad y Gobierno de Datos | C40: 0.5 | D40: =0.45*C35*C40 -> 0.0225 | I40: =SUM(I41:I43)*C40 -> 0.5 | J40: =SUM(J41:J43) -> 0.0225 | L40: =SUM(L41:L43)*C40 -> 0.375 | M40: =SUM(M41:M43) -> 0.016875
B41: 10.1 Deduplicación y normalización de registros | C41: 0.35 | D41: =0.45*C35*C40*C41 -> 0.007875 | E41: Detección y fusión automática de registros duplicados; normalización de campos clave (nombres, direcciones, CUIT). | F41: La migración desde 6 planillas generará inevitablemente duplicados sin herramientas de limpieza. | G41: Calidad del dato desde el día 1 — impacta directamente en la confianza del sistema. | H41: 1 | I41: =H41*C41 -> 0.35 | J41: =I41*D40 -> 0.007875 | K41: 0.75 | L41: =K41*C41 -> 0.2625 | M41: =L41*D40 -> 0.00590625
B42: 10.2 Validación y completitud de datos obligatorios | C42: 0.3 | D42: =0.45*C35*C40*C42 -> 0.00675 | E42: Reglas de validación que impiden guardar registros incompletos en campos críticos (CUIT, DNI, email, dirección). | F42: Datos incompletos en el CRM degradan la calidad de los reportes y las campañas. | G42: Control preventivo sobre la calidad del input en el origen. | H42: 1 | I42: =H42*C42 -> 0.3 | J42: =I42*D40 -> 0.00675 | K42: 0.75 | L42: =K42*C42 -> 0.225 | M42: =L42*D40 -> 0.0050625
B43: 10.3 Auditoría y trazabilidad de cambios en datos maestros | C43: 0.35 | D43: =0.45*C35*C40*C43 -> 0.007875 | E43: Log de quién modificó qué dato maestro, cuándo y con qué valor anterior — trazabilidad completa. | F43: Cumplimiento Ley 25.326: exige trazabilidad de modificaciones sobre datos personales. | G43: Requisito legal y de gobierno de datos en contexto argentino. | H43: 1 | I43: =H43*C43 -> 0.35 | J43: =I43*D40 -> 0.007875 | K43: 0.75 | L43: =K43*C43 -> 0.2625 | M43: =L43*D40 -> 0.00590625
B44: D. Gestión de Proyectos y Obra | C44: 0.15 | D44: =0.45*C44 -> 0.0675 | I44: =SUM(I45+I49)*C44 -> 0.109125 | J44: =SUM(J45+J49) -> 0.04910625 | L44: =SUM(L45+L49)*C44 -> 0.142125 | M44: =SUM(M45+M49) -> 0.06395625
B45: 11. Planificación y Control de Obra | C45: 0.7 | D45: =0.45*C44*C45 -> 0.04725 | I45: =SUM(I46:I48)*C45 -> 0.4725 | J45: =SUM(J46:J48) -> 0.03189375 | L45: =SUM(L46:L48)*C45 -> 0.6475 | M45: =SUM(M46:M48) -> 0.04370625
B46: 11.1 Proyectos con hitos, tareas y responsables | C46: 0.45 | D46: =0.45*C44*C45*C46 -> 0.0212625 | E46: Creación de proyectos con fases, hitos, tareas asignadas a responsables y fechas de cumplimiento. | F46: Hoy la coordinación de obra se hace por WhatsApp con 40-70 contratistas — sin trazabilidad. | G46: Clave para la escalabilidad operativa y la reducción de dependencia en personas clave. | H46: 0.75 | I46: =H46*C46 -> 0.3375 | J46: =I46*D45 -> 0.015946875 | K46: 1 | L46: =K46*C46 -> 0.45 | M46: =L46*D45 -> 0.0212625
B47: 11.2 Seguimiento de contratistas en campo | C47: 0.3 | D47: =0.45*C44*C45*C47 -> 0.014175 | E47: Control de avance y cumplimiento de subcontratistas: check-ins de obra, reportes de progreso y alertas de retraso. | F47: Alta dependencia de llamadas y decisiones ad hoc — riesgo de desvíos no detectados. | G47: Reduce riesgo operativo de obra y mejora la coordinación del equipo externo. | H47: 0.5 | I47: =H47*C47 -> 0.15 | J47: =I47*D45 -> 0.0070875 | K47: 0.75 | L47: =K47*C47 -> 0.225 | M47: =L47*D45 -> 0.01063125
B48: 11.3 Control de cronograma con Gantt / Timeline | C48: 0.25 | D48: =0.45*C44*C45*C48 -> 0.0118125 | E48: Visualización del cronograma de obra en formato Gantt con dependencias entre tareas y seguimiento de desvíos. | F48: Sin cronograma visual, los directivos no tienen visibilidad del estado real de avance. | G48: Herramienta estándar de gestión de proyectos — baseline de cualquier solución PM. | H48: 0.75 | I48: =H48*C48 -> 0.1875 | J48: =I48*D45 -> 0.008859375 | K48: 1 | L48: =K48*C48 -> 0.25 | M48: =L48*D45 -> 0.0118125
B49: 12. Documentación de Obra | C49: 0.3 | D49: =0.45*C44*C49 -> 0.02025 | I49: =SUM(I50:I51)*C49 -> 0.255 | J49: =SUM(J50:J51) -> 0.0172125 | L49: =SUM(L50:L51)*C49 -> 0.3 | M49: =SUM(M50:M51) -> 0.02025
B50: 12.1 Repositorio documental (planos, contratos, permisos) | C50: 0.6 | D50: =0.45*C44*C49*C50 -> 0.01215 | E50: Almacenamiento centralizado de documentos técnicos y legales con control de versiones y permisos de acceso. | F50: Actualmente documentación en papel, sin versiones ni trazabilidad — riesgo legal alto. | G50: Digitalización documental — reduce riesgo legal y mejora la eficiencia operativa. | H50: 0.75 | I50: =H50*C50 -> 0.45 | J50: =I50*D49 -> 0.0091125 | K50: 1 | L50: =K50*C50 -> 0.6 | M50: =L50*D49 -> 0.01215
B51: 12.2 Digitalización y acceso móvil a documentos | C51: 0.4 | D51: =0.45*C44*C49*C51 -> 0.0081 | E51: Acceso desde smartphones o tablets a planos, memorias y especificaciones técnicas desde el campo. | F51: Los responsables de obra en Los Cardales necesitan acceso remoto a documentación actualizada. | G51: Alineado con el requisito cloud-first y la operación desde múltiples locaciones. | H51: 1 | I51: =H51*C51 -> 0.4 | J51: =I51*D49 -> 0.0081 | K51: 1 | L51: =K51*C51 -> 0.4 | M51: =L51*D49 -> 0.0081
B52: E. Finanzas y Administración | C52: 0.15 | D52: =0.45*C52 -> 0.0675 | I52: =SUM(I53+I57)*C52 -> 0.129 | J52: =SUM(J53+J57) -> 0.05805 | L52: =SUM(L53+L57)*C52 -> 0.14325 | M52: =SUM(M53+M57) -> 0.0644625
B53: 13. Contabilidad Operativa | C53: 0.6 | D53: =0.45*C52*C53 -> 0.0405 | I53: =SUM(I54:I56)*C53 -> 0.51 | J53: =SUM(J54:J56) -> 0.034425 | L53: =SUM(L54:L56)*C53 -> 0.555 | M53: =SUM(M54:M56) -> 0.0374625
B54: 13.1 Registro automático de ingresos y gastos | C54: 0.4 | D54: =0.45*C52*C53*C54 -> 0.0162 | E54: Carga y categorización automática de transacciones desde las operaciones del CRM y proyectos. | F54: Hoy se carga manualmente en Excel con alto riesgo de error y demora. | G54: Reduce carga operativa y mejora la exactitud financiera. | H54: 1 | I54: =H54*C54 -> 0.4 | J54: =I54*D53 -> 0.0162 | K54: 1 | L54: =K54*C54 -> 0.4 | M54: =L54*D53 -> 0.0162
B55: 13.2 Facturación y comprobantes compatibles AFIP | C55: 0.3 | D55: =0.45*C52*C53*C55 -> 0.01215 | E55: Emisión de facturas electrónicas, recibos y comprobantes integrados con los requisitos de AFIP (factura A/B, CUIT, etc.). | F55: Operación 100% en Argentina — la compatibilidad AFIP no es opcional. | G55: Prerequisito legal; su ausencia obliga a mantener un sistema paralelo de facturación. | H55: 0.5 | I55: =H55*C55 -> 0.15 | J55: =I55*D53 -> 0.006075 | K55: 0.75 | L55: =K55*C55 -> 0.225 | M55: =L55*D53 -> 0.0091125
B56: 13.3 Flujo de caja y gestión de pagos | C56: 0.3 | D56: =0.45*C52*C53*C56 -> 0.01215 | E56: Proyección y control del flujo de caja: cobros por unidad, pagos a contratistas y saldos por proyecto. | F56: El flujo de caja es un riesgo crítico en proyectos inmobiliarios con ciclos de 24-36 meses. | G56: Control financiero básico que hoy se hace manualmente en planillas. | H56: 1 | I56: =H56*C56 -> 0.3 | J56: =I56*D53 -> 0.01215 | K56: 1 | L56: =K56*C56 -> 0.3 | M56: =L56*D53 -> 0.01215
B57: 14. Control de Costos de Proyecto | C57: 0.4 | D57: =0.45*C52*C57 -> 0.027 | I57: =SUM(I58:I59)*C57 -> 0.35 | J57: =SUM(J58:J59) -> 0.023625 | L57: =SUM(L58:L59)*C57 -> 0.4 | M57: =SUM(M58:M59) -> 0.027
B58: 14.1 Presupuesto vs. real por proyecto | C58: 0.5 | D58: =0.45*C52*C57*C58 -> 0.0135 | E58: Comparación en tiempo real del costo presupuestado vs. el ejecutado por proyecto, fase y contratista. | F58: Sin control de costos automático, los desvíos se detectan tarde, cuando el impacto ya es alto. | G58: Gestión financiera de proyectos — baseline en cualquier solución de PM+Finanzas integrada. | H58: 0.75 | I58: =H58*C58 -> 0.375 | J58: =I58*D57 -> 0.010125 | K58: 1 | L58: =K58*C58 -> 0.5 | M58: =L58*D57 -> 0.0135
B59: 14.2 Rentabilidad por proyecto y unidad de negocio | C59: 0.5 | D59: =0.45*C52*C57*C59 -> 0.0135 | E59: Cálculo de margen de rentabilidad por proyecto, desagregado por unidad (piso, lote, departamento). | F59: Inversora de Capilla no tiene hoy visibilidad de rentabilidad real por proyecto. | G59: Dato crítico para decisiones de inversión y de pricing en futuros proyectos. | H59: 1 | I59: =H59*C59 -> 0.5 | J59: =I59*D57 -> 0.0135 | K59: 1 | L59: =K59*C59 -> 0.5 | M59: =L59*D57 -> 0.0135
B60: TOTALES | C60: =SUM(C4+C21+C35+C44+C52) -> 1 | D60: =SUM(D4,D21,D35,D44,D52) -> 0.45 | I60: =SUM(I4+I21+I35+I44+I52) -> 0.920625 | J60: =SUM(J52+J44+J35+J21+J4) -> 0.41428125 | L60: =SUM(L4+L21+L35+L44+L52) -> 0.927375 | M60: =SUM(M52+M44+M35+M21+M4) -> 0.41731875

Sheet Matriz Técnica
B2: ASPECTO TECNICO | C2: Ponderación | D2: Peso relativo | E2: Detalle | F2: Comentarios | G2: Justificación | H2: MS Dynamics 365 | K2: Zoho One
C3: 0.15 | H3: Puntaje | I3: Puntaje Ponderado | J3: Aporte Relativo | K3: Puntaje | L3: Puntaje Ponderado | M3: Aporte Relativo
B4: A. Infraestructura | C4: 0.2 | D4: =C4*C3 -> 0.03 | I4: =SUM(I5+I10+I14)*C4 -> 0.2 | J4: =SUM(J5+J10+J14) -> 0.03 | L4: =SUM(L5+L10+L14)*C4 -> 0.2 | M4: =SUM(M5+M10+M14) -> 0.03
B5: 1. Cloud | C5: 0.5 | D5: =C5*C4*C3 -> 0.015 | I5: =SUM(I6:I9)*C5 -> 0.5 | J5: =SUM(J6:J9) -> 0.015 | L5: =SUM(L6:L9)*C5 -> 0.5 | M5: =SUM(M6:M9) -> 0.015
B6: 1.1 Despliegue SaaS Multi-Tenant | C6: 0.4 | D6: =C3*C4*C5*C6 -> 0.006 | E6: Plataforma alojada en la nube del proveedor, accesible desde cualquier navegador sin instalación local. El proveedor gestiona infraestructura, actualizaciones y mantenimiento. | F6: Inversora de Capilla no cuenta con infraestructura IT propia ni personal técnico interno — el modelo SaaS elimina ese requisito desde el inicio. | G6: El mandato cloud-first del RFP excluye soluciones on-premise; el SaaS multi-tenant garantiza actualizaciones automáticas y costos predecibles de operación. | H6: 1 | I6: =H6*C6 -> 0.4 | J6: =I6*D5 -> 0.006 | K6: 1 | L6: =K6*C6 -> 0.4 | M6: =L6*D5 -> 0.006
B7: 1.2 Alta disponibilidad (HA) | C7: 0.4 | D7: =C3*C4*C5*C7 -> 0.006 | E7: Arquitectura con redundancia activa que minimiza el tiempo de inactividad no planificado mediante failover automático entre nodos o regiones. | F7: Una caída del sistema durante el proceso de venta de una unidad puede generar pérdida de la operación y deterioro inmediato de la confianza del cliente. | G7: La alta disponibilidad es prerrequisito operativo para una empresa cuyo negocio core depende de la plataforma — sin ella el modelo digital pierde su promesa de valor. | H7: 1 | I7: =H7*C7 -> 0.4 | J7: =I7*D5 -> 0.006 | K7: 1 | L7: =K7*C7 -> 0.4 | M7: =L7*D5 -> 0.006
B8: 1.3 Escalabilidad automática | C8: 0.1 | D8: =C3*C4*C5*C8 -> 0.0015 | E8: Capacidad de la plataforma de ajustar automáticamente los recursos de cómputo ante picos de demanda sin intervención manual ni degradación del servicio. | F8: Aunque hoy son 5-15 usuarios, la empresa prevé crecer en volumen de proyectos y personal; la plataforma debe acompañar ese crecimiento sin migraciones costosas. | G8: Evita la necesidad de re-implementaciones al escalar y protege la inversión inicial — clave en una empresa en etapa de transformación y crecimiento. | H8: 1 | I8: =H8*C8 -> 0.1 | J8: =I8*D5 -> 0.0015 | K8: 1 | L8: =K8*C8 -> 0.1 | M8: =L8*D5 -> 0.0015
B9: 1.4 SLA ≥ 99,9% | C9: 0.1 | D9: =C3*C4*C5*C9 -> 0.0015 | E9: Compromiso contractual del proveedor de disponibilidad mínima del 99,9% mensual, equivalente a menos de 9 horas de inactividad no planificada al año. | F9: El RFP establece como requisito técnico un uptime de 99,5%; el nivel de exigencia 99,9% representa el estándar de referencia del mercado SaaS empresarial. | G9: Un SLA formalizado con penalidades establece responsabilidad del proveedor y protege a Inversora de Capilla ante interrupciones que afecten operaciones comerciales. | H9: 1 | I9: =H9*C9 -> 0.1 | J9: =I9*D5 -> 0.0015 | K9: 1 | L9: =K9*C9 -> 0.1 | M9: =L9*D5 -> 0.0015
B10: 2. Acceso | C10: 0.35 | D10: =C10*C4*C3 -> 0.0105 | I10: =SUM(I11:I13)*C10 -> 0.35 | J10: =SUM(J11:J13) -> 0.0105 | L10: =SUM(L11:L13)*C10 -> 0.35 | M10: =SUM(M11:M13) -> 0.0105
B11: 2.1 Acceso Web | C11: 0.6 | D11: =C3*C4*C10*C11 -> 0.0063 | E11: Interfaz de usuario accesible desde cualquier navegador estándar (Chrome, Firefox, Edge, Safari) sin plugins adicionales ni requisitos de sistema operativo específico. | F11: El equipo opera desde Buenos Aires y Los Cardales; el acceso web universal elimina barreras de dispositivo y ubicación para toda la operación. | G11: Requisito base del modelo cloud-first — sin acceso web universal no existe movilidad operativa ni la posibilidad de trabajar desde múltiples locaciones. | H11: 1 | I11: =H11*C11 -> 0.6 | J11: =I11*D10 -> 0.0063 | K11: 1 | L11: =K11*C11 -> 0.6 | M11: =L11*D10 -> 0.0063
B12: 2.2 Aplicación móvil | C12: 0.1 | D12: =C3*C4*C10*C12 -> 0.00105 | E12: Aplicación nativa o PWA para iOS y Android que permite operar las funcionalidades clave desde smartphones y tablets sin degradación de la experiencia de usuario. | F12: Los directivos y responsables de obra en Los Cardales requieren acceso móvil para operar sin depender de una PC de escritorio en campo. | G12: La operación en campo es un caso de uso central de Inversora de Capilla — sin app móvil funcional se pierden los beneficios del modelo digital para obra. | H12: 1 | I12: =H12*C12 -> 0.1 | J12: =I12*D10 -> 0.00105 | K12: 1 | L12: =K12*C12 -> 0.1 | M12: =L12*D10 -> 0.00105
B13: 2.3 Soporte multiplataforma | C13: 0.3 | D13: =C3*C4*C10*C13 -> 0.00315 | E13: Compatibilidad verificada con los principales sistemas operativos (Windows, macOS, Android, iOS) y navegadores del mercado sin pérdida de funcionalidad. | F13: El equipo de Inversora de Capilla usa distintos dispositivos sin un estándar corporativo definido — la diversidad tecnológica del equipo es la norma. | G13: La diversidad de dispositivos en una PyME sin IT hace crítica la compatibilidad amplia para garantizar adopción real y evitar exclusiones involuntarias. | H13: 1 | I13: =H13*C13 -> 0.3 | J13: =I13*D10 -> 0.00315 | K13: 1 | L13: =K13*C13 -> 0.3 | M13: =L13*D10 -> 0.00315
B14: 3. Rendimiento | C14: 0.15 | D14: =C14*C4*C3 -> 0.0045 | I14: =SUM(I15:I16)*C14 -> 0.15 | J14: =SUM(J15:J16) -> 0.0045 | L14: =SUM(L15:L16)*C14 -> 0.15 | M14: =SUM(M15:M16) -> 0.0045
B15: 3.1 Tiempo de respuesta configurable | C15: 0.5 | D15: =C3*C4*C14*C15 -> 0.00225 | E15: Capacidad de ajustar parámetros de performance (timeouts, caché, frecuencia de actualización) según necesidades operativas y condiciones de conectividad de la empresa. | F15: Conexiones desde Los Cardales pueden tener latencia variable — la configurabilidad permite adaptar la plataforma a esas condiciones de conectividad. | G15: La performance percibida impacta directamente en la tasa de adopción del sistema — un sistema lento es un sistema abandonado. | H15: 1 | I15: =H15*C15 -> 0.5 | J15: =I15*D14 -> 0.00225 | K15: 1 | L15: =K15*C15 -> 0.5 | M15: =L15*D14 -> 0.00225
B16: 3.2 Monitoreo de performance | C16: 0.5 | D16: =C3*C4*C14*C16 -> 0.00225 | E16: Panel o dashboard de métricas de performance del sistema: tiempos de carga, disponibilidad, errores y uso de recursos en tiempo real o near-real-time. | F16: Sin monitoreo, los problemas de performance solo se detectan cuando ya afectan al usuario; el diagnóstico proactivo reduce el impacto operativo. | G16: Habilita la gestión proactiva de la plataforma y la comunicación formal con el proveedor ante incumplimientos de SLA — condición de accountability técnico. | H16: 1 | I16: =H16*C16 -> 0.5 | J16: =I16*D14 -> 0.00225 | K16: 1 | L16: =K16*C16 -> 0.5 | M16: =L16*D14 -> 0.00225
B17: B. Integración | C17: 0.3 | D17: =C17*C3 -> 0.045 | I17: =SUM(I18+I22+I27)*C17 -> 0.282186 | J17: =SUM(J18+J22+J27) -> 0.0423279 | L17: =SUM(L18+L22+L27)*C17 -> 0.25937362 | M17: =SUM(M22+M27+M29) -> 0.03740625
B18: 4. APIs | C18: 0.05 | D18: =C18*C17*C3 -> 0.00225 | I18: =SUM(I19:I21)*C18 -> 0.049995 | J18: =SUM(J19+J20+J21) -> 0.002249775 | L18: =SUM(L19:L21)*C18 -> 0.04582875 | M18: =SUM(M19:M21) -> 0.0020622937
B19: 4.1 APIs REST nativas | C19: 0.3333 | D19: =C3*C17*C18*C19 -> 0.000749925 | E19: Conjunto de endpoints REST publicados nativamente por la plataforma para acceso programático a entidades, operaciones y datos desde sistemas externos. | F19: Inversora de Capilla puede necesitar integrar portales inmobiliarios (Properati, Zonaprop) o sistemas contables externos vía API en una segunda fase. | G19: Las APIs REST son el estándar de integración del ecosistema SaaS — su ausencia cierra la posibilidad de conectar con cualquier herramienta de terceros. | H19: 1 | I19: =H19*C19 -> 0.3333 | J19: =I19*D18 -> 0.000749925 | K19: 1 | L19: =K19*C19 -> 0.3333 | M19: =L19*D18 -> 0.000749925
B20: 4.2 APIs documentadas | C20: 0.3333 | D20: =C3*C17*C18*C20 -> 0.000749925 | E20: Documentación técnica completa y actualizada de los endpoints REST: especificación OpenAPI/Swagger, ejemplos de uso, autenticación y límites de tasa. | F20: Una API sin documentación adecuada requiere ingeniería inversa costosa, elevando el costo de integración para cualquier partner implementador o desarrollo interno. | G20: La calidad de la documentación define la velocidad y el costo de cualquier integración futura — es determinante del TCO real más allá del precio de lista. | H20: 1 | I20: =H20*C20 -> 0.3333 | J20: =I20*D18 -> 0.000749925 | K20: 0.75 | L20: =K20*C20 -> 0.249975 | M20: =L20*D18 -> 0.00056244375
B21: 4.3 Webhooks | C21: 0.3333 | D21: =C3*C17*C18*C21 -> 0.000749925 | E21: Mecanismo de notificación push que dispara llamadas HTTP a sistemas externos ante eventos internos de la plataforma (nuevo lead, cambio de estado, pago registrado). | F21: Los webhooks permiten automatizar flujos con herramientas externas (Zapier, Make, sistemas propios) sin polling constante que consuma recursos. | G21: Habilitan integraciones en tiempo real más eficientes que el polling periódico, reduciendo complejidad y costo operativo de cualquier integración futura. | H21: 1 | I21: =H21*C21 -> 0.3333 | J21: =I21*D18 -> 0.000749925 | K21: 1 | L21: =K21*C21 -> 0.3333 | M21: =L21*D18 -> 0.000749925
B22: 5. Datos | C22: 0.85 | D22: =C22*C17*C3 -> 0.03825 | I22: =SUM(I23:I26)*C22 -> 0.796875 | J22: =SUM(J23:J26) -> 0.035859375 | L22: =SUM(L23:L26)*C22 -> 0.74375 | M22: =SUM(M23:M26) -> 0.03346875
B23: 5.1 Importación masiva | C23: 0.25 | D23: =C3*C17*C22*C23 -> 0.0095625 | E23: Herramienta nativa para carga masiva de registros desde archivos CSV, Excel u otros formatos estructurados hacia las entidades clave de la plataforma. | F23: La migración desde las 6 planillas Excel actuales requiere importación masiva — sin esta capacidad la carga inicial es manual, lenta y propensa a errores. | G23: Condición técnica para que la migración de datos históricos sea viable, rápida y confiable desde el día 1 de operación del nuevo sistema. | H23: 1 | I23: =H23*C23 -> 0.25 | J23: =I23*D22 -> 0.0095625 | K23: 1 | L23: =K23*C23 -> 0.25 | M23: =L23*D22 -> 0.0095625
B24: 5.2 Exportación masiva | C24: 0.25 | D24: =C3*C17*C22*C24 -> 0.0095625 | E24: Capacidad de extraer la totalidad de los propios datos en formatos estándar (CSV, Excel, JSON) sin restricciones de volumen ni dependencia del proveedor. | F24: El derecho a exportar los propios datos es un principio de soberanía de datos — crítico para evitar vendor lock-in y proteger la continuidad del negocio. | G24: Protege ante un cambio de proveedor y garantiza el cumplimiento de la Ley 25.326 sobre habeas data y portabilidad de la información. | H24: 1 | I24: =H24*C24 -> 0.25 | J24: =I24*D22 -> 0.0095625 | K24: 1 | L24: =K24*C24 -> 0.25 | M24: =L24*D22 -> 0.0095625
B25: 5.3 ETL / ELT | C25: 0.25 | D25: =C3*C17*C22*C25 -> 0.0095625 | E25: Pipelines nativos o conectores certificados para extraer, transformar y cargar datos entre la plataforma y repositorios analíticos externos de forma automatizada. | F25: Sin ETL automatizado, el BI requiere exportaciones manuales periódicas que consumen tiempo y generan datos desactualizados para la toma de decisiones. | G25: Es el prerrequisito técnico para el análisis en tiempo real y la construcción de un repositorio analítico unificado — base del BI mencionado en el aspecto funcional. | H25: 1 | I25: =H25*C25 -> 0.25 | J25: =I25*D22 -> 0.0095625 | K25: 0.75 | L25: =K25*C25 -> 0.1875 | M25: =L25*D22 -> 0.007171875
B26: 5.4 Sincronización bidireccional | C26: 0.25 | D26: =C3*C17*C22*C26 -> 0.0095625 | E26: Capacidad de mantener datos coherentes en tiempo real entre la plataforma y sistemas externos (contabilidad, portales, ERP) con actualización en ambas direcciones. | F26: Un registro actualizado en el CRM debe reflejarse automáticamente en el sistema contable y viceversa — sin esto hay doble carga manual y riesgo de inconsistencias. | G26: Elimina la necesidad de mantener datos en paralelo en múltiples sistemas, reduciendo errores de ingreso y carga operativa del equipo administrativo. | H26: 0.75 | I26: =H26*C26 -> 0.1875 | J26: =I26*D22 -> 0.007171875 | K26: 0.75 | L26: =K26*C26 -> 0.1875 | M26: =L26*D22 -> 0.007171875
B27: 6. Ecosistema | C27: 0.1 | D27: =C27*C17*C3 -> 0.0045 | I27: =SUM(I28:I31)*C27 -> 0.09375 | J27: =SUM(J28:J31) -> 0.00421875 | L27: =SUM(L28:L31)*C27 -> 0.075 | M27: =SUM(M28:M31) -> 0.003375
B28: 6.1 Microsoft 365 | C28: 0.25 | D28: =C3*C17*C27*C28 -> 0.001125 | E28: Integración nativa con el ecosistema Microsoft 365: sincronización de correo (Outlook), calendario (Teams/Calendar), OneDrive y almacenamiento de documentos. | F28: Si el equipo ya usa Outlook o Teams, la integración reduce la curva de adopción al conectar el CRM con herramientas que el equipo ya conoce y utiliza a diario. | G28: Microsoft 365 es el entorno de productividad más difundido en PyMEs argentinas — la integración nativa acelera la adopción y reduce la resistencia al cambio. | H28: 1 | I28: =H28*C28 -> 0.25 | J28: =I28*D27 -> 0.001125 | K28: 0.75 | L28: =K28*C28 -> 0.1875 | M28: =L28*D27 -> 0.00084375
B29: 6.2 Power BI | C29: 0.25 | D29: =C3*C17*C27*C29 -> 0.001125 | E29: Conector certificado con Microsoft Power BI para visualización avanzada de datos y construcción de reportes personalizados sobre los datos de la plataforma. | F29: Si la empresa ya utiliza o planea incorporar Power BI, la integración nativa evita duplicar el esfuerzo de análisis y extrae mayor valor del dato ya capturado. | G29: Power BI es la herramienta de BI más utilizada en el segmento empresarial; la integración nativa amplía las capacidades analíticas sin costo adicional de desarrollo. | H29: 1 | I29: =H29*C29 -> 0.25 | J29: =I29*D27 -> 0.001125 | K29: 0.5 | L29: =K29*C29 -> 0.125 | M29: =L29*D27 -> 0.0005625
B30: 6.3 Google Workspace | C30: 0.25 | D30: =C3*C17*C27*C30 -> 0.001125 | E30: Integración nativa con Google Workspace: sincronización de Gmail, Google Calendar, Google Drive y Google Meet para el equipo que use este ecosistema. | F30: Una parte del equipo puede usar Gmail y Google Calendar como herramientas primarias — la integración sincroniza actividad sin duplicación manual de registros. | G30: Google Workspace es alternativa frecuente en PyMEs; la integración garantiza flexibilidad ante distintas preferencias tecnológicas del equipo. | H30: 0.75 | I30: =H30*C30 -> 0.1875 | J30: =I30*D27 -> 0.00084375 | K30: 1 | L30: =K30*C30 -> 0.25 | M30: =L30*D27 -> 0.001125
B31: 6.4 ERP externos | C31: 0.25 | D31: =C3*C17*C27*C31 -> 0.001125 | E31: Conectores o adaptadores para integración con sistemas ERP presentes en el mercado argentino (Tango Gestión, Bejerman, SAP B1 u otros de uso frecuente local). | F31: Inversora de Capilla puede tener o incorporar un sistema contable/ERP — la integración evita doble carga de datos entre el CRM y la herramienta contable. | G31: La coexistencia de CRM y ERP es frecuente en PyMEs argentinas — la integración nativa reduce el costo total de integración y los errores de doble ingreso. | H31: 1 | I31: =H31*C31 -> 0.25 | J31: =I31*D27 -> 0.001125 | K31: 0.75 | L31: =K31*C31 -> 0.1875 | M31: =L31*D27 -> 0.00084375
B32: C. Seguridad | C32: 0.35 | D32: =C32*C3 -> 0.0525 | I32: =SUM(I33+I37+I40+I45)*C32 -> 0.35 | J32: =SUM(J33+J40+J37+J45) -> 0.0525 | L32: =SUM(L33+L37+L40+L45)*C32 -> 0.314125 | M32: =SUM(M33+M40+M37+M45) -> 0.04711875
B33: 7. Identidad | C33: 0.4 | D33: =C33*C32*C3 -> 0.021 | I33: =SUM(I34:I36)*C33 -> 0.4 | J33: =SUM(J34:J36) -> 0.021 | L33: =SUM(L34:L36)*C33 -> 0.36 | M33: =SUM(M34:M36) -> 0.0189
B34: 7.1 MFA | C34: 0.6 | D34: =C3*C32*C33*C34 -> 0.0126 | E34: Autenticación multifactor obligatoria o configurable mediante código SMS, autenticador TOTP (Google/Microsoft Authenticator) o llaves de seguridad físicas. | F34: Inversora de Capilla maneja datos de clientes con CUIT, DNI y datos patrimoniales — el MFA es la primera línea de defensa ante accesos no autorizados. | G34: Requisito explícito del RFP en el aspecto técnico; el MFA es el control de identidad más efectivo contra ataques de credential stuffing y phishing. | H34: 1 | I34: =H34*C34 -> 0.6 | J34: =I34*D33 -> 0.0126 | K34: 1 | L34: =K34*C34 -> 0.6 | M34: =L34*D33 -> 0.0126
B35: 7.2 SSO | C35: 0.3 | D35: =C3*C32*C33*C35 -> 0.0063 | E35: Single Sign-On que permite acceder a la plataforma con las mismas credenciales corporativas (Microsoft, Google) sin gestionar contraseñas adicionales. | F35: El SSO simplifica la gestión de accesos y reduce la fricción de adopción para el equipo — una credencial menos que recordar y gestionar. | G35: Mejora la experiencia del usuario y centraliza la gestión de identidad, reduciendo el riesgo de contraseñas débiles o reutilizadas en cuentas sensibles. | H35: 1 | I35: =H35*C35 -> 0.3 | J35: =I35*D33 -> 0.0063 | K35: 0.75 | L35: =K35*C35 -> 0.225 | M35: =L35*D33 -> 0.004725
B36: 7.3 Integración con Azure AD | C36: 0.1 | D36: =C3*C32*C33*C36 -> 0.0021 | E36: Integración nativa con Azure Active Directory / Microsoft Entra ID para autenticación federada, gestión de grupos y políticas de acceso corporativas. | F36: Relevante si la empresa escala hacia el ecosistema Microsoft 365; permite gestionar usuarios desde un directorio centralizado sin duplicar la administración. | G36: Azure AD es el directorio corporativo más extendido en el mercado empresarial argentino — la integración nativa es un diferenciador de madurez técnica en evaluación. | H36: 1 | I36: =H36*C36 -> 0.1 | J36: =I36*D33 -> 0.0021 | K36: 0.75 | L36: =K36*C36 -> 0.075 | M36: =L36*D33 -> 0.001575
B37: 8. Autorización | C37: 0.3 | D37: =C37*C32*C3 -> 0.01575 | I37: =SUM(I38:I39)*C37 -> 0.3 | J37: =SUM(J38:J39) -> 0.01575 | L37: =SUM(L38:L39)*C37 -> 0.2625 | M37: =SUM(M38:M39) -> 0.01378125
B38: 8.1 RBAC | C38: 0.5 | D38: =C3*C32*C37*C38 -> 0.007875 | E38: Control de acceso basado en roles (Role-Based Access Control) que define qué funcionalidades y datos puede ver o modificar cada perfil de usuario de la plataforma. | F38: En Inversora de Capilla coexisten perfiles distintos (director, vendedor, responsable de obra, administrador) con necesidades de acceso claramente diferenciadas. | G38: Requisito explícito del RFP; el RBAC garantiza que cada usuario vea solo lo que necesita, reduciendo riesgos de modificaciones no autorizadas sobre datos críticos. | H38: 1 | I38: =H38*C38 -> 0.5 | J38: =I38*D37 -> 0.007875 | K38: 1 | L38: =K38*C38 -> 0.5 | M38: =L38*D37 -> 0.007875
B39: 8.2 Roles personalizables | C39: 0.5 | D39: =C3*C32*C37*C39 -> 0.007875 | E39: Capacidad de crear y modificar roles a medida, más allá de los perfiles predefinidos, para adaptarse a la estructura organizativa específica de la empresa. | F39: La estructura de Inversora de Capilla no responde a jerarquías corporativas estándar — roles rígidos pueden no mapear correctamente sus necesidades operativas reales. | G39: Los roles personalizables garantizan que los controles de acceso reflejen la realidad operativa sin forzar adaptaciones estructurales en la empresa. | H39: 1 | I39: =H39*C39 -> 0.5 | J39: =I39*D37 -> 0.007875 | K39: 0.75 | L39: =K39*C39 -> 0.375 | M39: =L39*D37 -> 0.00590625
B40: 9. Datos | C40: 0.2 | D40: =C40*C32*C3 -> 0.0105 | I40: =SUM(I41:I44)*C40 -> 0.2 | J40: =SUM(J41:J44) -> 0.0105 | L40: =SUM(L41:L44)*C40 -> 0.175 | M40: =SUM(M41:M44) -> 0.0091875
B41: 9.1 Cifrado en tránsito (TLS) | C41: 0.25 | D41: =C3*C32*C40*C41 -> 0.002625 | E41: Toda la comunicación entre el cliente (navegador/app) y los servidores de la plataforma está cifrada con TLS 1.2 o superior, sin excepciones. | F41: El tráfico de datos sensibles (datos de clientes, operaciones, documentos) sobre redes públicas o móviles requiere cifrado para evitar interceptación. | G41: TLS es el estándar mínimo de seguridad en comunicaciones web; su ausencia invalida cualquier declaración de seguridad de la plataforma en el mercado actual. | H41: 1 | I41: =H41*C41 -> 0.25 | J41: =I41*D40 -> 0.002625 | K41: 1 | L41: =K41*C41 -> 0.25 | M41: =L41*D40 -> 0.002625
B42: 9.2 Cifrado en reposo | C42: 0.25 | D42: =C3*C32*C40*C42 -> 0.002625 | E42: Los datos almacenados en bases de datos y sistemas de archivos del proveedor están cifrados con AES-256 o equivalente, incluso ante acceso físico al hardware. | F42: Los datos de clientes y operaciones de Inversora de Capilla tienen valor patrimonial y están sujetos a la Ley 25.326 de protección de datos personales. | G42: El cifrado en reposo protege los datos ante brechas en la infraestructura del proveedor y es requisito de cumplimiento normativo en el contexto argentino. | H42: 1 | I42: =H42*C42 -> 0.25 | J42: =I42*D40 -> 0.002625 | K42: 1 | L42: =K42*C42 -> 0.25 | M42: =L42*D40 -> 0.002625
B43: 9.3 Auditoría de cambios | C43: 0.25 | D43: =C3*C32*C40*C43 -> 0.002625 | E43: Log inmutable y consultable de todas las modificaciones realizadas sobre datos del sistema: quién cambió qué, cuándo y cuál era el valor anterior. | F43: En transacciones inmobiliarias de alto valor, la trazabilidad de cambios es crítica para resolver disputas y cumplir con eventuales auditorías externas. | G43: Requisito de la Ley 25.326 (trazabilidad de modificaciones de datos personales) y condición de gobierno de datos de cualquier plataforma de gestión madura. | H43: 1 | I43: =H43*C43 -> 0.25 | J43: =I43*D40 -> 0.002625 | K43: 0.75 | L43: =K43*C43 -> 0.1875 | M43: =L43*D40 -> 0.00196875
B44: 9.4 Trazabilidad completa | C44: 0.25 | D44: =C3*C32*C40*C44 -> 0.002625 | E44: Registro de auditoría de todas las acciones del sistema: accesos, consultas, exportaciones, eliminaciones y cambios de configuración, con retención configurable. | F44: La trazabilidad completa habilita la detección de accesos indebidos y la reconstrucción del estado del sistema ante incidentes de seguridad o disputas. | G44: Complemento del cifrado y el RBAC — sin trazabilidad no hay gobierno efectivo de los datos ni capacidad de respuesta ante incidentes de seguridad. | H44: 1 | I44: =H44*C44 -> 0.25 | J44: =I44*D40 -> 0.002625 | K44: 0.75 | L44: =K44*C44 -> 0.1875 | M44: =L44*D40 -> 0.00196875
B45: 10. Compliance | C45: 0.1 | D45: =C45*C32*C3 -> 0.00525 | I45: =SUM(I46:I46)*C45 -> 0.1 | J45: =SUM(J46:J46) -> 0.00525 | L45: =SUM(L46:L46)*C45 -> 0.1 | M45: =SUM(M46:M46) -> 0.00525
B46: 10.1 Logs exportables | C46: 1 | D46: =C3*C32*C45*C46 -> 0.00525 | E46: Los logs de auditoría son exportables en formatos estándar (CSV, JSON, Syslog) para análisis externo, retención propia o integración con herramientas de monitoreo. | F46: Exportar los propios logs garantiza que Inversora de Capilla pueda retener evidencia de cumplimiento de forma independiente al proveedor. | G46: Los logs exportables son condición para auditorías externas y para cumplir con eventuales requisitos regulatorios sin depender de la voluntad del proveedor. | H46: 1 | I46: =H46*C46 -> 1 | J46: =I46*D45 -> 0.00525 | K46: 1 | L46: =K46*C46 -> 1 | M46: =L46*D45 -> 0.00525
B47: D. Operación | C47: 0.15 | D47: =C47*C3 -> 0.0225 | I47: =SUM(I48+I52+I56)*C47 -> 0.14165208 | J47: =SUM(J52+J48+J56) -> 0.021247813 | L47: =SUM(L48+L52+L56)*C47 -> 0.13331917 | M47: =SUM(M52+M48+M56) -> 0.019997875
B48: 11. Administración | C48: 0.3333 | D48: =C3*C47*C48 -> 0.00749925 | I48: =SUM(I49:I51)*C48 -> 0.30549445 | J48: =SUM(J49:J51) -> 0.0068736251 | L48: =SUM(L49:L51)*C48 -> 0.33326667 | M48: =SUM(M49:M51) -> 0.0074985001
B49: 11.1 Configuración sin código | C49: 0.3333 | D49: =C3*C47*C48*C49 -> 0.0024995 | E49: Capacidad de personalizar formularios, flujos, campos y reglas de negocio desde interfaces visuales sin requerir programación ni asistencia técnica del proveedor. | F49: Inversora de Capilla no tiene equipo IT — toda configuración post-implementación debe ser ejecutable por usuarios de negocio sin conocimiento técnico. | G49: La autonomía operativa reduce la dependencia del proveedor para ajustes cotidianos y disminuye el costo total de operación a lo largo del tiempo. | H49: 0.75 | I49: =H49*C49 -> 0.249975 | J49: =I49*D48 -> 0.001874625 | K49: 1 | L49: =K49*C49 -> 0.3333 | M49: =L49*D48 -> 0.0024995
B50: 11.2 Capacidad de parametrización de workflows sin desarrollo | C50: 0.3333 | D50: =C3*C47*C48*C50 -> 0.0024995 | E50: Editor visual de flujos de trabajo que permite crear, modificar y activar automatizaciones de procesos sin intervención de desarrollo externo. | F50: Los workflows de seguimiento comercial y coordinación de obra deben poder ajustarse a medida que la empresa evoluciona, sin tickets al soporte del proveedor. | G50: La flexibilidad de workflows es clave para la adopción continua — un sistema rígido que no evoluciona con el negocio termina siendo relegado o abandonado. | H50: 1 | I50: =H50*C50 -> 0.3333 | J50: =I50*D48 -> 0.0024995 | K50: 1 | L50: =K50*C50 -> 0.3333 | M50: =L50*D48 -> 0.0024995
B51: 11.3 Gestión de usuarios | C51: 0.3333 | D51: =C3*C47*C48*C51 -> 0.0024995 | E51: Panel de administración para crear, modificar, desactivar y asignar roles a usuarios sin asistencia del proveedor, con control total por el administrador local. | F51: La rotación de personal en ventas y obra requiere poder gestionar accesos con agilidad, sin depender de tickets al soporte del proveedor para cada cambio. | G51: La autogestión de usuarios es un requisito operativo básico — su ausencia genera fricciones y costos de administración innecesarios en la operación diaria. | H51: 1 | I51: =H51*C51 -> 0.3333 | J51: =I51*D48 -> 0.0024995 | K51: 1 | L51: =K51*C51 -> 0.3333 | M51: =L51*D48 -> 0.0024995
B52: 12. Continuidad | C52: 0.3333 | D52: =C3*C47*C52 -> 0.00749925 | I52: =SUM(I53:I55)*C52 -> 0.33326667 | J52: =SUM(J53:J55) -> 0.0074985001 | L52: =SUM(L53:L55)*C52 -> 0.27772222 | M52: =SUM(M53:M55) -> 0.0062487501
B53: 12.1 Backup automático | C53: 0.3333 | D53: =C3*C47*C52*C53 -> 0.0024995 | E53: Respaldo automático de todos los datos con frecuencia mínima diaria, retención configurable y verificación de integridad sin intervención manual del usuario. | F53: Inversora de Capilla no tiene capacidad técnica para gestionar backups manualmente — la automatización es condición básica de continuidad operativa. | G53: El backup automático protege contra pérdida de datos por errores humanos, fallas del sistema o incidentes de seguridad — es un requisito de continuidad básico. | H53: 1 | I53: =H53*C53 -> 0.3333 | J53: =I53*D52 -> 0.0024995 | K53: 1 | L53: =K53*C53 -> 0.3333 | M53: =L53*D52 -> 0.0024995
B54: 12.2 Disaster Recovery | C54: 0.3333 | D54: =C3*C47*C52*C54 -> 0.0024995 | E54: Plan documentado de recuperación ante desastres con RTO y RPO definidos y garantizados contractualmente, incluyendo pruebas periódicas del proceso. | F54: Una caída prolongada del sistema durante una operación inmobiliaria puede tener consecuencias legales y financieras graves para Inversora de Capilla. | G54: El DR es la contraparte del SLA — garantiza que ante un incidente mayor el proveedor restablece el servicio dentro de plazos conocidos y contractualmente exigibles. | H54: 1 | I54: =H54*C54 -> 0.3333 | J54: =I54*D52 -> 0.0024995 | K54: 0.75 | L54: =K54*C54 -> 0.249975 | M54: =L54*D52 -> 0.001874625
B55: 12.3 Versionado de información | C55: 0.3333 | D55: =C3*C47*C52*C55 -> 0.0024995 | E55: Capacidad de mantener y acceder a versiones históricas de documentos y registros clave, permitiendo recuperar estados anteriores ante errores o disputas. | F55: En transacciones inmobiliarias donde los datos evolucionan (precios, condiciones, planos), el historial de versiones es evidencia ante controversias contractuales. | G55: El versionado complementa el backup — permite recuperar no solo el sistema sino el estado específico de un registro en un momento dado, con precisión quirúrgica. | H55: 1 | I55: =H55*C55 -> 0.3333 | J55: =I55*D52 -> 0.0024995 | K55: 0.75 | L55: =K55*C55 -> 0.249975 | M55: =L55*D52 -> 0.001874625
B56: 13. Gobierno | C56: 0.3334 | D56: =C3*C47*C56 -> 0.0075015 | I56: =SUM(I57:I59)*C56 -> 0.3055861 | J56: =SUM(J57:J59) -> 0.0068756874 | L56: =SUM(L57:L59)*C56 -> 0.27780555 | M56: =SUM(M57:M59) -> 0.0062506249
B57: 13.1 Auditoría operativa | C57: 0.3333 | D57: =C3*C47*C56*C57 -> 0.0025002499 | E57: Registro de las acciones operativas de los usuarios (creación, modificación, eliminación de registros) accesible para el administrador de la plataforma. | F57: La auditoría operativa permite identificar errores, detectar usos indebidos y cumplir con requerimientos de accountability en las operaciones comerciales. | G57: En un equipo sin supervisión técnica permanente, la auditoría operativa es el mecanismo de control más accesible y accionable para los directivos de la empresa. | H57: 1 | I57: =H57*C57 -> 0.3333 | J57: =I57*D56 -> 0.0025002499 | K57: 0.75 | L57: =K57*C57 -> 0.249975 | M57: =L57*D56 -> 0.0018751875
B58: 13.2 Gestión de cambios | C58: 0.3333 | D58: =C3*C47*C56*C58 -> 0.0025002499 | E58: Proceso y herramientas para documentar, aprobar y controlar cambios en la configuración y parametrización, evitando modificaciones no autorizadas en producción. | F58: Cambios no controlados en la configuración pueden generar inconsistencias en datos o flujos que afecten operaciones comerciales en curso sin posibilidad de rastreo. | G58: Un proceso liviano de gestión de cambios es fundamental para mantener la estabilidad operativa del sistema a lo largo del tiempo, incluso en una PyME. | H58: 0.75 | I58: =H58*C58 -> 0.249975 | J58: =I58*D56 -> 0.0018751875 | K58: 0.75 | L58: =K58*C58 -> 0.249975 | M58: =L58*D56 -> 0.0018751875
B59: 13.3 Monitoreo y alertas | C59: 0.3333 | D59: =C3*C47*C56*C59 -> 0.0025002499 | E59: Panel de monitoreo del estado operativo de la plataforma con alertas proactivas ante anomalías, caídas de servicio o degradaciones de performance. | F59: Sin monitoreo proactivo, los problemas de la plataforma solo se detectan cuando ya impactan en la operación del equipo, aumentando el tiempo de inactividad. | G59: El monitoreo activo reduce el tiempo de detección y respuesta ante incidentes, minimizando el impacto en la continuidad operativa del negocio. | H59: 1 | I59: =H59*C59 -> 0.3333 | J59: =I59*D56 -> 0.0025002499 | K59: 1 | L59: =K59*C59 -> 0.3333 | M59: =L59*D56 -> 0.0025002499
B60: TOTAL | C60: =C4+C17+C32+C47 -> 1 | D60: =D4+D17+D32+D47 -> 0.15 | I60: =I4+I17+I32+I47 -> 0.97383808 | J60: =SUM(J4+J17+J32+J47) -> 0.14607571 | L60: =L4+L17+L32+L47 -> 0.90681779 | M60: =SUM(M4+M17+M32+M47) -> 0.13452288
B62: Categoría | C62: Peso
B63: Seguridad | C63: 0.35
B64: Integración | C64: 0.3
B65: Infraestructura | C65: 0.2
B66: Operación | C66: 0.15

Sheet Matriz Económica
B2: ASPECTO ECONOMICO | C2: Ponderación | D2: Peso relativo | E2: Detalle | F2: Comentarios | G2: Justificación | H2: MS Dynamics 365 | K2: Zoho One
C3: 0.2 | H3: Puntaje | I3: Puntaje Ponderado | J3: Aporte Relativo | K3: Puntaje | L3: Puntaje Ponderado | M3: Aporte Relativo
B4: A. Costos iniciales de adquisición | C4: 0.4 | D4: =C3*C4 -> 0.08 | I4: =SUM(I5+I10)*C4 -> 0.225 | J4: =SUM(J5+J10) -> 0.045 | L4: =SUM(L5+L10)*C4 -> 0.3625 | M4: =SUM(M5+M10) -> 0.0725
B5: 1. Licenciamiento | C5: 0.5 | D5: =C3*C4*C5 -> 0.04 | I5: =SUM(I6:I9)*C5 -> 0.28125 | J5: =SUM(J6:J9) -> 0.0225 | L5: =SUM(L6:L9)*C5 -> 0.4375 | M5: =SUM(M6:M9) -> 0.035
B6: 1.1 Costo por usuario | C6: 0.25 | D6: =C3*C4*C5*C6 -> 0.01 | E6: Precio mensual por usuario activo en el plan base de la plataforma, en modalidad SaaS, expresado en USD o ARS según política del proveedor. | F6: Con 5-15 usuarios en el escenario de Inversora de Capilla, el costo por usuario es el principal driver del OPEX mensual de la plataforma. | G6: El costo por usuario define la accesibilidad económica del modelo para una PyME argentina con presupuesto acotado en contexto de alta inflación. | H6: 0.25 | I6: =H6*C6 -> 0.0625 | J6: =I6*D5 -> 0.0025 | K6: 0.75 | L6: =K6*C6 -> 0.1875 | M6: =L6*D5 -> 0.0075
B7: 1.2 Costo por administrador | C7: 0.25 | D7: =C3*C4*C5*C7 -> 0.01 | E7: Diferenciación de precio entre usuarios estándar y usuarios administradores o con acceso a módulos premium, si la plataforma establece esta distinción. | F7: Algunos proveedores cobran diferente por usuarios con permisos de administración — esto puede elevar el costo si los directivos necesitan acceso completo. | G7: Una estructura de precios que penaliza la administración dificulta la autogestión y eleva el TCO real frente al precio de lista publicado. | H7: 0.75 | I7: =H7*C7 -> 0.1875 | J7: =I7*D5 -> 0.0075 | K7: 1 | L7: =K7*C7 -> 0.25 | M7: =L7*D5 -> 0.01
B8: 1.3 Licencias incluidas | C8: 0.25 | D8: =C3*C4*C5*C8 -> 0.01 | E8: Cantidad de módulos, funcionalidades y aplicaciones incluidas en el precio base sin cargos adicionales — cobertura real del paquete base contratado. | F8: Un precio base bajo con módulos clave excluidos puede resultar más caro que un plan all-inclusive al sumar los add-ons necesarios para la operación. | G8: La exhaustividad del paquete base determina el costo real de la solución — un modelo modular fragmentado eleva el TCO de forma no prevista en la propuesta. | H8: 0.5 | I8: =H8*C8 -> 0.125 | J8: =I8*D5 -> 0.005 | K8: 1 | L8: =K8*C8 -> 0.25 | M8: =L8*D5 -> 0.01
B9: 1.4 Escalabilidad de licencias | C9: 0.25 | D9: =C3*C4*C5*C9 -> 0.01 | E9: Flexibilidad para agregar o reducir usuarios sin penalidades significativas ni contratos de largo plazo, adaptándose al crecimiento o contracción del equipo. | F9: Una empresa en crecimiento como Inversora de Capilla necesita poder escalar el número de usuarios sin renegociar contratos complejos con el proveedor. | G9: La elasticidad del licenciamiento es crítica para una PyME cuyo equipo puede crecer rápido — la rigidez contractual genera costos ocultos de crecimiento. | H9: 0.75 | I9: =H9*C9 -> 0.1875 | J9: =I9*D5 -> 0.0075 | K9: 0.75 | L9: =K9*C9 -> 0.1875 | M9: =L9*D5 -> 0.0075
B10: 2. Implementación | C10: 0.5 | D10: =C3*C4*C10 -> 0.04 | I10: =SUM(I11:I14)*C10 -> 0.28125 | J10: =SUM(J11:J14) -> 0.0225 | L10: =SUM(L11:L14)*C10 -> 0.46875 | M10: =SUM(M11:M14) -> 0.0375
B11: 2.1 Setup inicial | C11: 0.25 | D11: =C3*C4*C5*C11 -> 0.01 | E11: Costo único de configuración inicial: creación del entorno, setup base y activación del tenant, cobrado por el proveedor o su partner implementador. | F11: El setup inicial es un CAPEX que impacta en la liquidez inicial del proyecto — debe ser transparente y predecible desde la propuesta del proveedor. | G11: Los costos de setup varían ampliamente entre proveedores (desde $0 hasta miles de USD) y son determinantes del costo real total del primer año de operación. | H11: 0.75 | I11: =H11*C11 -> 0.1875 | J11: =I11*D10 -> 0.0075 | K11: 1 | L11: =K11*C11 -> 0.25 | M11: =L11*D10 -> 0.01
B12: 2.2 Parametrización | C12: 0.25 | D12: =C3*C4*C5*C12 -> 0.01 | E12: Costo de configuración a medida: adaptación de flujos, campos, formularios y reglas de negocio específicas de Inversora de Capilla a la plataforma elegida. | F12: Cuanto más parametrización requiera la plataforma para el contexto inmobiliario argentino, mayor será el CAPEX inicial de implementación del proyecto. | G12: La parametrización inicial es el principal CAPEX variable — su estimación precisa define si el proyecto es viable dentro del presupuesto asignado. | H12: 0.25 | I12: =H12*C12 -> 0.0625 | J12: =I12*D10 -> 0.0025 | K12: 0.75 | L12: =K12*C12 -> 0.1875 | M12: =L12*D10 -> 0.0075
B13: 2.3 Migración de datos | C13: 0.25 | D13: =C3*C4*C5*C13 -> 0.01 | E13: Costo del proceso de extracción, limpieza, transformación y carga de los datos existentes (6 planillas Excel) hacia la nueva plataforma. | F13: La migración de datos históricos de clientes, proyectos y operaciones es crítica para no perder trazabilidad al pasar al nuevo sistema — y tiene un costo real. | G13: Un costo de migración elevado o mal estimado puede convertirse en el principal obstáculo económico del proyecto de transformación digital. | H13: 0.75 | I13: =H13*C13 -> 0.1875 | J13: =I13*D10 -> 0.0075 | K13: 1 | L13: =K13*C13 -> 0.25 | M13: =L13*D10 -> 0.01
B14: 2.4 Integraciones iniciales | C14: 0.25 | D14: =C3*C4*C5*C14 -> 0.01 | E14: Costo de desarrollo o configuración de las integraciones necesarias desde el día 1: sistemas contables, portales inmobiliarios o herramientas ya en uso. | F14: Si las integraciones clave no están incluidas en el setup, su costo adicional puede superar el precio de licencia del primer año de operación. | G14: Las integraciones iniciales son el costo oculto más frecuente en implementaciones SaaS — su estimación explícita es condición de comparabilidad real entre propuestas. | H14: 0.5 | I14: =H14*C14 -> 0.125 | J14: =I14*D10 -> 0.005 | K14: 1 | L14: =K14*C14 -> 0.25 | M14: =L14*D10 -> 0.01
B15: B. Costos operativos y mantenimiento | C15: 0.4 | D15: =C3*C15 -> 0.08 | I15: =SUM(I16+I19+I23)*C15 -> 0.31332 | J15: =SUM(J16+J19+J23) -> 0.062664 | L15: =SUM(L16+L19+L23)*C15 -> 0.35332 | M15: =SUM(M16+M19+M23) -> 0.070664
B16: 3. Suscripción | C16: 0.4 | D16: =C3*C15*C16 -> 0.032 | I16: =SUM(I17:I18)*C16 -> 0.25 | J16: =SUM(J17:J18) -> 0.02 | L16: =SUM(L17:L18)*C16 -> 0.4 | M16: =SUM(M17:M18) -> 0.032
B17: 3.1 Pago mensual | C17: 0.5 | D17: =C3*C15*C16*C17 -> 0.016 | E17: Precio de la suscripción en modalidad mensual sin compromiso anual, que ofrece mayor flexibilidad pero generalmente a un precio unitario más elevado. | F17: La modalidad mensual es preferible en contextos de alta inflación o incertidumbre — permite salir del contrato sin penalidades si la solución no cumple. | G17: En el contexto económico argentino, la flexibilidad del pago mensual tiene valor real aunque implique un precio nominal mayor al compromiso anual. | H17: 0.75 | I17: =H17*C17 -> 0.375 | J17: =I17*D16 -> 0.012 | K17: 1 | L17: =K17*C17 -> 0.5 | M17: =L17*D16 -> 0.016
B18: 3.2 Pago anual | C18: 0.5 | D18: =C3*C15*C16*C17 -> 0.016 | E18: Precio de la suscripción en modalidad anual prepagada, que generalmente ofrece un descuento del 15-20% sobre la tarifa mensual equivalente. | F18: El pago anual reduce el OPEX mensual pero implica un desembolso inicial mayor y un compromiso de 12 meses con el proveedor seleccionado. | G18: La relación precio anual/mensual define el incentivo a comprometerse con el proveedor — un descuento significativo mejora el TCO proyectado a 3 años. | H18: 0.5 | I18: =H18*C18 -> 0.25 | J18: =I18*D16 -> 0.008 | K18: 1 | L18: =K18*C18 -> 0.5 | M18: =L18*D16 -> 0.016
B19: 4. Infraestructura | C19: 0.4 | D19: =C3*C15*C19 -> 0.032 | I19: =SUM(I20:I22)*C19 -> 0.3333 | J19: =SUM(J20:J22) -> 0.026664 | L19: =SUM(L20:L22)*C19 -> 0.3333 | M19: =SUM(M20:M22) -> 0.026664
B20: 4.1 Hosting | C20: 0.3333 | D20: =C3*C15*C19*C20 -> 0.0106656 | E20: Costo del alojamiento en la nube del proveedor, generalmente incluido en la suscripción SaaS — se evalúa si hay cargos adicionales por región o disponibilidad. | F20: En el modelo SaaS el hosting debe estar incluido — cualquier cargo separado por hosting eleva el TCO real respecto al precio de lista publicado. | G20: La transparencia en el costo de hosting es un indicador de honestidad en el pricing — los cargos ocultos de infraestructura son una señal de alerta comercial. | H20: 1 | I20: =H20*C20 -> 0.3333 | J20: =I20*D19 -> 0.0106656 | K20: 1 | L20: =K20*C20 -> 0.3333 | M20: =L20*D19 -> 0.0106656
B21: 4.2 Almacenamiento | C21: 0.3333 | D21: =C3*C15*C19*C21 -> 0.0106656 | E21: Límite de almacenamiento incluido en el plan base y costo por GB adicional — relevante dado el volumen de planos, documentos y fotos de obra previsto. | F21: El almacenamiento de planos, documentación técnica y fotos de obra puede superar rápidamente los límites del plan base si no se considera desde el inicio. | G21: El costo de almacenamiento adicional es un OPEX creciente que puede distorsionar el TCO proyectado si no se incluye en la estimación inicial del proyecto. | H21: 1 | I21: =H21*C21 -> 0.3333 | J21: =I21*D19 -> 0.0106656 | K21: 0.75 | L21: =K21*C21 -> 0.249975 | M21: =L21*D19 -> 0.0079992
B22: 4.3 Consumo adicional | C22: 0.3333 | D22: =C3*C15*C19*C22 -> 0.0106656 | E22: Cargos variables por uso intensivo: cantidad de registros, transacciones de API, envíos de email masivo u otras métricas de consumo fuera del plan base. | F22: Los cargos por consumo adicional son el componente más impredecible del TCO — generan facturas sorpresivas que dificultan la planificación presupuestaria. | G22: La previsibilidad del OPEX es crítica en una PyME argentina con presupuesto ajustado — los modelos de pricing por consumo generan incertidumbre financiera real. | H22: 0.5 | I22: =H22*C22 -> 0.16665 | J22: =I22*D19 -> 0.0053328 | K22: 0.75 | L22: =K22*C22 -> 0.249975 | M22: =L22*D19 -> 0.0079992
B23: 5. Soporte | C23: 0.2 | D23: =C3*C15*C23 -> 0.016 | I23: =SUM(I24:I25)*C23 -> 0.2 | J23: =SUM(J24:J25) -> 0.016 | L23: =SUM(L24:L25)*C23 -> 0.15 | M23: =SUM(M24:M25) -> 0.012
B24: 5.1 Soporte estándar | C24: 0.5 | D24: =C3*C15*C23*C24 -> 0.008 | E24: Plan de soporte incluido en la suscripción base: canales disponibles (email, chat, teléfono), horarios de atención y SLA de respuesta estándar garantizado. | F24: El soporte estándar define el nivel de asistencia disponible sin costo adicional — su calidad es determinante para una empresa sin IT propio. | G24: Evaluar el soporte incluido evita descubrir tardíamente que la asistencia necesaria solo está disponible en planes premium con costo adicional significativo. | H24: 1 | I24: =H24*C24 -> 0.5 | J24: =I24*D23 -> 0.008 | K24: 1 | L24: =K24*C24 -> 0.5 | M24: =L24*D23 -> 0.008
B25: 5.2 Soporte premium | C25: 0.5 | D25: =C3*C15*C23*C25 -> 0.008 | E25: Costo y cobertura del plan de soporte avanzado: SLA garantizado, gestor de cuenta dedicado, onboarding personalizado y prioridad en resolución de incidentes. | F25: Para una PyME sin IT interno, el soporte premium puede ser una inversión justificada si el estándar no garantiza tiempos de respuesta operativamente aceptables. | G25: El diferencial de precio entre soporte estándar y premium debe evaluarse contra el riesgo operativo de no tener asistencia prioritaria en momentos críticos. | H25: 1 | I25: =H25*C25 -> 0.5 | J25: =I25*D23 -> 0.008 | K25: 0.5 | L25: =K25*C25 -> 0.25 | M25: =L25*D23 -> 0.004
B26: C. Costos de Evolución | C26: 0.2 | D26: =C3*C26 -> 0.04 | I26: =SUM(I27+I31)*C26 -> 0.09999 | J26: =SUM(J27+J31) -> 0.019998 | L26: =SUM(L27+L31)*C26 -> 0.183315 | M26: =SUM(M27+M31) -> 0.036663
B27: 6. Crecimiento | C27: 0.5 | D27: =C3*C26*C27 -> 0.02 | I27: =SUM(I28:I30)*C27 -> 0.2083125 | J27: =SUM(J28:J30) -> 0.0083325 | L27: =SUM(L28:L30)*C27 -> 0.4582875 | M27: =SUM(M28:M30) -> 0.0183315
B28: 6.1 Usuarios adicionales | C28: 0.3333 | D28: =C3*C26*C27*C28 -> 0.006666 | E28: Precio unitario de agregar usuarios más allá del plan base contratado, incluyendo posibles cambios de tier o renegociaciones de contrato necesarias. | F28: Si Inversora de Capilla crece de 5 a 15 usuarios, el costo incremental por usuario define si el plan actual es sostenible o requiere migrar a un tier superior. | G28: El costo de escalar usuarios es un proxy del costo de crecimiento del negocio — debe ser lineal y predecible para no sorprender en la planificación financiera. | H28: 0.25 | I28: =H28*C28 -> 0.083325 | J28: =I28*D27 -> 0.0016665 | K28: 0.75 | L28: =K28*C28 -> 0.249975 | M28: =L28*D27 -> 0.0049995
B29: 6.2 Módulos adicionales | C29: 0.3333 | D29: =C3*C26*C27*C29 -> 0.006666 | E29: Precio de activar módulos o funcionalidades no incluidas en el plan base, como firma digital, inteligencia artificial o gestión documental avanzada. | F29: La necesidad de agregar módulos clave post-implementación puede duplicar el costo inicial del proyecto si no se evalúa en la propuesta original del proveedor. | G29: Los módulos adicionales son el mecanismo de upselling más frecuente en SaaS — su precio y disponibilidad deben evaluarse como parte del TCO a 3 años. | H29: 0.25 | I29: =H29*C29 -> 0.083325 | J29: =I29*D27 -> 0.0016665 | K29: 1 | L29: =K29*C29 -> 0.3333 | M29: =L29*D27 -> 0.006666
B30: 6.3 Ambientes adicionales | C30: 0.3333 | D30: =C3*C26*C27*C30 -> 0.006666 | E30: Costo de contar con entornos separados para pruebas o staging, además del ambiente de producción incluido en el plan base del proveedor. | F30: Un ambiente de pruebas separado permite testear configuraciones sin riesgo sobre datos productivos — práctica recomendada aunque tenga costo adicional. | G30: Operar sin ambiente de pruebas en una PyME es aceptable inicialmente, pero el costo de incorporarlo debe conocerse para la planificación futura del sistema. | H30: 0.75 | I30: =H30*C30 -> 0.249975 | J30: =I30*D27 -> 0.0049995 | K30: 1 | L30: =K30*C30 -> 0.3333 | M30: =L30*D27 -> 0.006666
B31: 7. Desarrollo | C31: 0.5 | D31: =C3*C26*C31 -> 0.02 | I31: =SUM(I32:I34)*C31 -> 0.2916375 | J31: =SUM(J32:J34) -> 0.0116655 | L31: =SUM(L32:L34)*C31 -> 0.4582875 | M31: =SUM(M32:M34) -> 0.0183315
B32: 7.1 Customizaciones | C32: 0.3333 | D32: =C3*C26*C31*C32 -> 0.006666 | E32: Costo de desarrollo de funcionalidades a medida o adaptaciones específicas del negocio no cubiertas por la configuración estándar de la plataforma. | F32: Las customizaciones tienen un costo de desarrollo inicial y un costo de mantenimiento futuro ante cada actualización de la plataforma — deben minimizarse. | G32: Cada customización introduce deuda técnica y dependencia del proveedor — su costo real incluye el mantenimiento a lo largo del ciclo de vida del sistema. | H32: 0.25 | I32: =H32*C32 -> 0.083325 | J32: =I32*D31 -> 0.0016665 | K32: 0.75 | L32: =K32*C32 -> 0.249975 | M32: =L32*D31 -> 0.0049995
B33: 7.2 Automatizaciones | C33: 0.3333 | D33: =C3*C26*C31*C33 -> 0.006666 | E33: Costo de crear o ampliar automatizaciones de flujos de trabajo más allá de las incluidas en el plan, por servicios del proveedor o desarrollo propio. | F33: Las automatizaciones son el componente de mayor ROI en la transformación digital — su costo de implementación debe evaluarse contra el ahorro operativo generado. | G33: Una plataforma que cobra caro por automatizaciones desincentiva su uso, limitando uno de los principales beneficios concretos de la digitalización. | H33: 0.5 | I33: =H33*C33 -> 0.16665 | J33: =I33*D31 -> 0.003333 | K33: 1 | L33: =K33*C33 -> 0.3333 | M33: =L33*D31 -> 0.006666
B34: 7.3 APIs adicionales | C34: 0.3333 | D34: =C3*C26*C31*C34 -> 0.006666 | E34: Costo de consumo de APIs más allá del límite incluido en el plan, o de acceder a APIs avanzadas disponibles solo en tiers superiores de la plataforma. | F34: Si las integraciones con portales inmobiliarios o sistemas externos requieren alto volumen de llamadas API, el costo adicional puede ser significativo. | G34: El costo de APIs adicionales define la viabilidad económica de integraciones futuras — debe evaluarse en el contexto del roadmap de integración de la empresa. | H34: 1 | I34: =H34*C34 -> 0.3333 | J34: =I34*D31 -> 0.006666 | K34: 1 | L34: =K34*C34 -> 0.3333 | M34: =L34*D31 -> 0.006666
B35: TOTAL | C35: =C4+C15+C26 -> 1 | D35: =D4+D15+D26 -> 0.2 | I35: =I4+I15+I26 -> 0.63831 | J35: =J4+J15+J26 -> 0.127662 | L35: =L4+L15+L26 -> 0.899135 | M35: =M4+M15+M26 -> 0.179827
B38: Categoría | C38: Peso
B39: Costos iniciales de adquisición | C39: 0.4
B40: Costos operativos y mantenimiento | C40: 0.4
B41: Costos de Evolución | C41: 0.2
B43: Escalas:
B45: Aspecto Económico — Escala adaptada | E45: Costo por usuario
B46: Puntaje | C46: Descripción | E46: Cumplimiento | F46: Valor
B47: 1 | C47: Muy competitivo | E47: 1 | F47: ≤ USD 40
B48: 0.75 | C48: Competitivo | E48: 0.75 | F48: >40 y ≤60
B49: 0.5 | C49: Aceptable | E49: 0.5 | F49: >60 y ≤90
B50: 0.25 | C50: Elevado | E50: 0.25 | F50: >90 y ≤120
B51: 0 | C51: Inviable | E51: 0 | F51: >120
B53: Licencias
B54: Puntaje | C54: Licencia mensual | E54: Costos de Implementación
B55: 1 | C55: ≤ USD 50 por usuario | E55: (Aplica a: setup, parametrización, migración, integraciones)
B56: 0.75 | C56: USD 51–75 | E56: Cumplimiento | F56: Criterio
B57: 0.5 | C57: USD 76–100 | E57: 1 | F57: ≤ USD 5.000
B58: 0.25 | C58: USD 101–150 | E58: 0.75 | F58: USD 5.001 – 10.000
B59: 0 | C59: > USD 150 | E59: 0.5 | F59: USD 10.001 – 15.000
E60: 0.25 | F60: USD 15.001 – 20.000
B61: Coste Total de Propiedad (TCO) a 3 años | E61: 0 | F61: > USD 20.000
B62: Puntaje | C62: TCO
B63: 1 | C63: ≤ USD 10.000 | E63: Costos Operativos
B64: 0.75 | C64: USD 10.001–15.000 | E64: (Aplica a: pago mensual, pago anual)
B65: 0.5 | C65: USD 15.001–20.000 | E65: Cumplimiento | F65: Criterio
B66: 0.25 | C66: USD 20.001–25.000 | E66: 1 | F66: ≤ USD 500 mensuales
B67: 0 | C67: > USD 25.000 | E67: 0.75 | F67: USD 501 – 1.000
E68: 0.5 | F68: USD 1.001 – 1.500
B69: Infraestructura y Servicios Asociados | E69: 0.25 | F69: USD 1.501 – 2.000
B70: (Aplica a: hosting, almacenamiento, consumos adicionales) | E70: 0 | F70: > USD 2.000
B71: Cumplimiento | C71: Criterio
B72: 1 | C72: Todos los servicios incluidos sin costos adicionales relevantes
B73: 0.75 | C73: Costos adicionales menores (<10% del valor anual)
B74: 0.5 | C74: Costos adicionales moderados (10%-20%)
B75: 0.25 | C75: Costos adicionales altos (20%-30%)
B76: 0 | C76: Costos adicionales >30%
B78: Soporte y Mantenimiento
B79: (Aplica a: soporte estándar y premium)
B80: Cumplimiento | C80: Criterio
B81: 1 | C81: Incluido sin cargo
B82: 0.75 | C82: Costo ≤ 10% del valor anual de licencias
B83: 0.5 | C83: Entre 10% y 20%
B84: 0.25 | C84: Entre 20% y 30%
B85: 0 | C85: >30%

Sheet Matriz Proveedores
B2: ASPECTO PROVEEDOR | C2: Ponderación | D2: Peso relativo | E2: Detalle | F2: Comentarios | G2: Justificación | H2: MS Dynamics 365 | K2: Zoho One
C3: 0.2 | H3: Puntaje | I3: Puntaje Ponderado | J3: Aporte Relativo | K3: Puntaje | L3: Puntaje Ponderado | M3: Aporte Relativo
B4: A. Trayectoria y solidez | C4: 0.25 | D4: =C3*C4 -> 0.05 | I4: =SUM(I5+I9+I12)*C4 -> 0.24302361 | J4: =SUM(J5+J9+J12) -> 0.048604722 | L4: =SUM(L5+L9+L12)*C4 -> 0.21524931 | M4: =SUM(M5+M9+M12) -> 0.043049861
B5: 1. Trayectoria | C5: 0.3333 | D5: =C3*C4*C5 -> 0.016665 | I5: =SUM(I6:I8)*C5 -> 0.30549445 | J5: =SUM(J6:J8) -> 0.015274722 | L5: =SUM(L6:L8)*C5 -> 0.27772222 | M5: =SUM(M6:M8) -> 0.013886111
B6: 1.1 Años en el mercado | C6: 0.3333 | D6: =C3*C4*C5*C6 -> 0.0055544445 | E6: Antigüedad del proveedor desde su fundación o desde el lanzamiento comercial del producto evaluado, como indicador de madurez y estabilidad en el mercado. | F6: Un proveedor con menos de 5 años representa mayor riesgo de discontinuidad o cambios disruptivos en el producto y su política comercial hacia clientes existentes. | G6: La antigüedad correlaciona con la estabilidad del producto, la madurez del soporte y la solidez financiera — factores críticos para una inversión de largo plazo. | H6: 0.75 | I6: =H6*C6 -> 0.249975 | J6: =I6*D5 -> 0.0041658334 | K6: 0.75 | L6: =K6*C6 -> 0.249975 | M6: =L6*D5 -> 0.0041658334
B7: 1.2 Presencia internacional | C7: 0.3333 | D7: =C3*C4*C5*C7 -> 0.0055544445 | E7: Operación del proveedor en múltiples países o regiones, con subsidiarias, partners certificados o clientes activos fuera de su mercado de origen. | F7: La presencia internacional indica escala y capacidad de inversión en I+D — reduce el riesgo de que decisiones locales afecten la continuidad del producto. | G7: Un proveedor con presencia global tiene mayor resistencia ante crisis regionales y más recursos para mantener y evolucionar el producto a largo plazo. | H7: 1 | I7: =H7*C7 -> 0.3333 | J7: =I7*D5 -> 0.0055544445 | K7: 1 | L7: =K7*C7 -> 0.3333 | M7: =L7*D5 -> 0.0055544445
B8: 1.3 Estabilidad financiera | C8: 0.3333 | D8: =C3*C4*C5*C8 -> 0.0055544445 | E8: Solidez financiera del proveedor: cotización pública, respaldo de inversores institucionales, ingresos recurrentes documentados o ausencia de reestructuraciones recientes. | F8: Un proveedor con dificultades financieras puede abandonar el producto, ser adquirido o degradar el servicio — riesgo crítico para la continuidad operativa. | G8: La estabilidad financiera es un componente del riesgo de vendor lock-in — un proveedor financieramente débil puede obligar a una migración forzada y costosa. | H8: 1 | I8: =H8*C8 -> 0.3333 | J8: =I8*D5 -> 0.0055544445 | K8: 0.75 | L8: =K8*C8 -> 0.249975 | M8: =L8*D5 -> 0.0041658334
B9: 2. Escala | C9: 0.3333 | D9: =C3*C4*C9 -> 0.016665 | I9: =SUM(I10:I11)*C9 -> 0.3333 | J9: =SUM(J10:J11) -> 0.016665 | L9: =SUM(L10:L11)*C9 -> 0.3333 | M9: =SUM(M10:M11) -> 0.016665
B10: 2.1 Cantidad de clientes | C10: 0.5 | D10: =C3*C4*C9*C10 -> 0.0083325 | E10: Número total de empresas clientes activas de la plataforma a nivel global o en la región, como indicador de adopción y validación en el mercado. | F10: Una base amplia de clientes indica que la plataforma superó la etapa experimental y cuenta con comunidad, recursos de soporte y ecosistema consolidado. | G10: La escala de clientes es un proxy de la madurez del producto y de la capacidad del proveedor de mantener un servicio de calidad de forma sostenible. | H10: 1 | I10: =H10*C10 -> 0.5 | J10: =I10*D9 -> 0.0083325 | K10: 1 | L10: =K10*C10 -> 0.5 | M10: =L10*D9 -> 0.0083325
B11: 2.2 Cantidad de usuarios | C11: 0.5 | D11: =C3*C4*C9*C11 -> 0.0083325 | E11: Número total de usuarios activos en la plataforma, que refleja la adopción real y la capacidad de la infraestructura para soportar carga a escala. | F11: Una plataforma con millones de usuarios activos ha probado su escalabilidad y estabilidad bajo carga real — garantía de infraestructura sólida para el cliente. | G11: La cantidad de usuarios activos valida la viabilidad técnica y comercial del proveedor a largo plazo — indicador complementario al número de clientes. | H11: 1 | I11: =H11*C11 -> 0.5 | J11: =I11*D9 -> 0.0083325 | K11: 1 | L11: =K11*C11 -> 0.5 | M11: =L11*D9 -> 0.0083325
B12: 3. Certificaciones y Compliance | C12: 0.3333 | D12: =C3*C4*C12 -> 0.016665 | I12: =SUM(I13:I14)*C12 -> 0.3333 | J12: =SUM(J13:J14) -> 0.016665 | L12: =SUM(L13:L14)*C12 -> 0.249975 | M12: =SUM(M13:M14) -> 0.01249875
B13: 3.1 Certificaciones y cumplimiento normativo | C13: 0.5 | D13: ='Matriz Técnica'!C3*'Matriz Técnica'!C32*'Matriz Técnica'!C45*C13 -> 0.002625 | E13: La plataforma o el proveedor cuenta con certificación ISO/IEC 27001 o equivalentes, que acredita un Sistema de Gestión de Seguridad de la Información auditado por terceros. | F13: La certificación reduce el riesgo de contratar a un proveedor con prácticas de seguridad insuficientes, ya que implica auditorías periódicas independientes. | G13: En ausencia de un equipo IT interno, la certificación del proveedor es la única garantía objetiva y verificable de sus controles de seguridad. | H13: 1 | I13: =H13*C13 -> 0.5 | J13: =I13*D12 -> 0.0083325 | K13: 0.75 | L13: =K13*C13 -> 0.375 | M13: =L13*D12 -> 0.006249375
B14: 3.2 GDPR | C14: 0.5 | D14: ='Matriz Técnica'!C3*'Matriz Técnica'!C32*'Matriz Técnica'!C45*C14 -> 0.002625 | E14: La plataforma cumple con los principios del GDPR europeo: minimización de datos, derecho al olvido, portabilidad y consentimiento explícito del titular. | F14: El GDPR es el estándar internacional de referencia en protección de datos; su cumplimiento indica madurez del proveedor en prácticas de privacidad. | G14: Aunque Inversora de Capilla opera bajo Ley 25.326, la alineación con GDPR garantiza un nivel de protección superior al mínimo legal local exigido. | H14: 1 | I14: =H14*C14 -> 0.5 | J14: =I14*D12 -> 0.0083325 | K14: 0.75 | L14: =K14*C14 -> 0.375 | M14: =L14*D12 -> 0.006249375
B15: B. Experiencia | C15: 0.3 | D15: =C3*C15 -> 0.06 | I15: =SUM(I16+I20)*C15 -> 0.285 | J15: =SUM(J16+J20) -> 0.057 | L15: =SUM(L16+L20)*C15 -> 0.285 | M15: =SUM(M16+M20) -> 0.057
B16: 4. Industria | C16: 0.6 | D16: =C3*C15*C16 -> 0.036 | I16: =SUM(I17:I19)*C16 -> 0.6 | J16: =SUM(J17:J19) -> 0.036 | L16: =SUM(L17:L19)*C16 -> 0.6 | M16: =SUM(M17:M19) -> 0.036
B17: 4.1 Casos inmobiliarios | C17: 0.3333 | D17: =C3*C15*C16*C17 -> 0.0119988 | E17: Experiencia documentada del proveedor o su red de partners en implementaciones para empresas del sector Real Estate, PropTech o construcción. | F17: Una plataforma sin casos en el sector inmobiliario requiere mayor esfuerzo de adaptación para cubrir los procesos específicos del negocio de Inversora de Capilla. | G17: La experiencia sectorial reduce el riesgo de implementación, acelera la configuración y garantiza que los flujos del negocio inmobiliario estén contemplados. | H17: =(H18*C18+H19*C19)/(C18+C19) -> 1 | I17: =H17*C17 -> 0.3333 | J17: =I17*D16 -> 0.0119988 | K17: =(K18*C18+K19*C19)/(C18+C19) -> 1 | L17: =K17*C17 -> 0.3333 | M17: =L17*D16 -> 0.0119988
B18: 4.2 Casos PyME | C18: 0.3333 | D18: =C3*C15*C16*C18 -> 0.0119988 | E18: Historial de implementaciones exitosas en empresas de tamaño similar (5-50 usuarios, sin IT interno) con perfiles operativos y presupuestos comparables. | F18: Un proveedor orientado a grandes empresas puede sobredimensionar la solución en complejidad, costo y requerimientos para una PyME como Inversora de Capilla. | G18: La experiencia con PyMEs garantiza que el modelo de implementación, soporte y pricing esté calibrado para la capacidad real de absorción de la empresa. | H18: 1 | I18: =H18*C18 -> 0.3333 | J18: =I18*D16 -> 0.0119988 | K18: 1 | L18: =K18*C18 -> 0.3333 | M18: =L18*D16 -> 0.0119988
B19: 4.3 Casos Argentina | C19: 0.3334 | D19: =C3*C15*C16*C19 -> 0.0120024 | E19: Implementaciones activas o referenciables en empresas argentinas, con comprensión del contexto normativo local (AFIP, Ley 25.326, operatoria en ARS). | F19: El contexto argentino tiene particularidades operativas y regulatorias que un proveedor sin experiencia local puede subestimar, generando brechas en la solución. | G19: La experiencia en Argentina es un diferenciador crítico — garantiza comprensión de las restricciones locales y soporte sin adaptaciones de alto costo adicional. | H19: 1 | I19: =H19*C19 -> 0.3334 | J19: =I19*D16 -> 0.0120024 | K19: 1 | L19: =K19*C19 -> 0.3334 | M19: =L19*D16 -> 0.0120024
B20: 5. Referencias | C20: 0.4 | D20: =C3*C15*C20 -> 0.024 | I20: =SUM(I21:I22)*C20 -> 0.35 | J20: =SUM(J21:J22) -> 0.021 | L20: =SUM(L21:L22)*C20 -> 0.35 | M20: =SUM(M21:M22) -> 0.021
B21: 5.1 Clientes de referencia | C21: 0.5 | D21: =C3*C15*C20*C21 -> 0.012 | E21: Disponibilidad del proveedor de proveer contactos de clientes reales dispuestos a ser consultados, idealmente del sector inmobiliario o PyME argentina. | F21: Las referencias directas permiten validar la experiencia real del proveedor más allá de los materiales de marketing — son la evidencia más confiable disponible. | G21: La disposición a proveer referencias es un indicador de confianza del proveedor — los que tienen implementaciones exitosas no dudan en compartir sus casos. | H21: 0.75 | I21: =H21*C21 -> 0.375 | J21: =I21*D20 -> 0.009 | K21: 0.75 | L21: =K21*C21 -> 0.375 | M21: =L21*D20 -> 0.009
B22: 5.2 Casos documentados | C22: 0.5 | D22: =C3*C15*C20*C22 -> 0.012 | E22: Disponibilidad de casos de éxito formalmente documentados: descripción del cliente, problemática resuelta, solución implementada y resultados medibles obtenidos. | F22: Los casos documentados permiten evaluar la metodología de implementación del proveedor y la tipología de empresas con las que trabaja habitualmente. | G22: Los casos documentados son evidencia verificable de capacidad — su ausencia o superficialidad es una señal de alerta sobre la solidez real del proveedor. | H22: 1 | I22: =H22*C22 -> 0.5 | J22: =I22*D20 -> 0.012 | K22: 1 | L22: =K22*C22 -> 0.5 | M22: =L22*D20 -> 0.012
B23: C. Ecosistema | C23: 0.15 | D23: =C3*C23 -> 0.03 | I23: =SUM(I24+I28)*C23 -> 0.1499925 | J23: =SUM(J24+J28) -> 0.0299985 | L23: =SUM(L24+L28)*C23 -> 0.11249437 | M23: =SUM(M24+M28) -> 0.022498875
B24: 6. Partners | C24: 0.5 | D24: =C3*C23*C24 -> 0.015 | I24: =SUM(I25:I27)*C24 -> 0.49995 | J24: =SUM(J25:J27) -> 0.0149985 | L24: =SUM(L25:L27)*C24 -> 0.3749625 | M24: =SUM(M25:M27) -> 0.011248875
B25: 6.1 Red de partners | C25: 0.3333 | D25: =C3*C23*C24*C25 -> 0.0049995 | E25: Cantidad y calidad de empresas partners certificadas por el proveedor para implementar, personalizar y soportar la plataforma en la región latinoamericana. | F25: Una red de partners activa en Argentina garantiza que Inversora de Capilla puede elegir entre varios implementadores sin depender del proveedor directo. | G25: La competencia entre partners reduce el costo de implementación y aumenta la calidad — un proveedor sin partners locales es un punto único de falla operativo. | H25: 1 | I25: =H25*C25 -> 0.3333 | J25: =I25*D24 -> 0.0049995 | K25: 0.75 | L25: =K25*C25 -> 0.249975 | M25: =L25*D24 -> 0.003749625
B26: 6.2 Consultores certificados | C26: 0.3333 | D26: =C3*C23*C24*C26 -> 0.0049995 | E26: Existencia de un programa de certificación formal para consultores implementadores, con exámenes, niveles de competencia y renovación periódica. | F26: La certificación formal garantiza un nivel mínimo de competencia técnica en el partner contratado — sin ella la calidad de implementación es impredecible. | G26: Un programa de certificación sólido protege a Inversora de Capilla ante implementaciones deficientes al establecer un estándar verificable de calidad. | H26: 1 | I26: =H26*C26 -> 0.3333 | J26: =I26*D24 -> 0.0049995 | K26: 0.75 | L26: =K26*C26 -> 0.249975 | M26: =L26*D24 -> 0.003749625
B27: 6.3 Implementadores locales | C27: 0.3333 | D27: =C3*C23*C24*C27 -> 0.0049995 | E27: Presencia de partners implementadores con operación física en Argentina, con capacidad de trabajo presencial y conocimiento del mercado local. | F27: Un implementador local puede realizar visitas presenciales, comprende el contexto de negocio argentino y opera en el mismo huso horario que el cliente. | G27: La proximidad física del implementador reduce el tiempo de respuesta ante problemas y facilita la transferencia de conocimiento al equipo de la empresa. | H27: 1 | I27: =H27*C27 -> 0.3333 | J27: =I27*D24 -> 0.0049995 | K27: 0.75 | L27: =K27*C27 -> 0.249975 | M27: =L27*D24 -> 0.003749625
B28: 7. Marketplace | C28: 0.5 | D28: =C3*C23*C28 -> 0.015 | I28: =SUM(I29:I30)*C28 -> 0.5 | J28: =SUM(J29:J30) -> 0.015 | L28: =SUM(L29:L30)*C28 -> 0.375 | M28: =SUM(M29:M30) -> 0.01125
B29: 7.1 Marketplace de aplicaciones | C29: 0.5 | D29: =C3*C23*C28*C29 -> 0.0075 | E29: Tienda oficial de aplicaciones y extensiones de terceros para la plataforma, con herramientas complementarias validadas disponibles sin desarrollo adicional. | F29: Un marketplace activo indica que el ecosistema del proveedor es maduro y que la comunidad de desarrolladores ve valor en construir sobre su plataforma. | G29: Un marketplace rico reduce el costo de incorporar funcionalidades específicas al reutilizar soluciones existentes en lugar de desarrollarlas desde cero. | H29: 1 | I29: =H29*C29 -> 0.5 | J29: =I29*D28 -> 0.0075 | K29: 0.75 | L29: =K29*C29 -> 0.375 | M29: =L29*D28 -> 0.005625
B30: 7.2 Add-ons disponibles | C30: 0.5 | D30: =C3*C23*C28*C30 -> 0.0075 | E30: Cantidad y relevancia de las extensiones o add-ons disponibles específicamente para el sector inmobiliario o PropTech dentro del marketplace del proveedor. | F30: La disponibilidad de add-ons específicos para Real Estate puede cubrir necesidades funcionales sin recurrir a desarrollo personalizado de alto costo. | G30: Los add-ons sectoriales representan una vía de expansión funcional de bajo riesgo — su disponibilidad define el potencial de evolución futura de la solución. | H30: 1 | I30: =H30*C30 -> 0.5 | J30: =I30*D28 -> 0.0075 | K30: 0.75 | L30: =K30*C30 -> 0.375 | M30: =L30*D28 -> 0.005625
B31: D. Soporte | C31: 0.2 | D31: =C3*C31 -> 0.04 | I31: =SUM(I32+I36)*C31 -> 0.183325 | J31: =SUM(J32+J36) -> 0.036665 | L31: =SUM(L32+L36)*C31 -> 0.170825 | M31: =SUM(M32+M36) -> 0.034165
B32: 8. Atención | C32: 0.5 | D32: =C3*C31*C32 -> 0.02 | I32: =SUM(I33:I35)*C32 -> 0.416625 | J32: =SUM(J33:J35) -> 0.016665 | L32: =SUM(L33:L35)*C32 -> 0.416625 | M32: =SUM(M33:M35) -> 0.016665
B33: 8.1 Soporte en español | C33: 0.3333 | D33: =C3*C31*C32*C33 -> 0.006666 | E33: Disponibilidad de agentes de soporte técnico y documentación en español, sin requerir el uso del inglés para resolver incidentes o consultas técnicas. | F33: El equipo de Inversora de Capilla no tiene perfil técnico — el soporte en español es condición para que el equipo resuelva problemas de forma autónoma. | G33: El soporte en el idioma del usuario es un factor crítico de adopción — un soporte técnico que no puede ser usado efectivamente no aporta valor real. | H33: 0.75 | I33: =H33*C33 -> 0.249975 | J33: =I33*D32 -> 0.0049995 | K33: 0.75 | L33: =K33*C33 -> 0.249975 | M33: =L33*D32 -> 0.0049995
B34: 8.2 Soporte regional | C34: 0.3333 | D34: =C3*C31*C32*C34 -> 0.006666 | E34: Oficina o equipo de soporte dedicado para América Latina, con conocimiento del contexto regulatorio, operativo y cultural de la región. | F34: El soporte regional comprende las particularidades del mercado argentino (AFIP, inflación, operatoria en pesos) sin necesidad de explicarlas en cada consulta. | G34: El soporte regional reduce el tiempo de resolución de incidentes con componentes locales y garantiza alineación con la normativa vigente en Argentina. | H34: 0.75 | I34: =H34*C34 -> 0.249975 | J34: =I34*D32 -> 0.0049995 | K34: 1 | L34: =K34*C34 -> 0.3333 | M34: =L34*D32 -> 0.006666
B35: 8.3 Horario extendido | C35: 0.3333 | D35: =C3*C31*C32*C35 -> 0.006666 | E35: Disponibilidad de soporte técnico más allá del horario hábil estándar (9-18 hs), incluyendo fines de semana o guardias para incidentes críticos. | F35: Las operaciones inmobiliarias pueden cerrar fuera del horario comercial — un incidente en el sistema en ese momento puede impedir concretar una transacción. | G35: El horario extendido de soporte reduce el riesgo operativo ante incidentes fuera del horario estándar — diferenciador clave en sectores con operaciones extendidas. | H35: 1 | I35: =H35*C35 -> 0.3333 | J35: =I35*D32 -> 0.006666 | K35: 0.75 | L35: =K35*C35 -> 0.249975 | M35: =L35*D32 -> 0.0049995
B36: 9. Servicio | C36: 0.5 | D36: =C3*C31*C36 -> 0.02 | I36: =SUM(I37:I38)*C36 -> 0.5 | J36: =SUM(J37:J38) -> 0.02 | L36: =SUM(L37:L38)*C36 -> 0.4375 | M36: =SUM(M37:M38) -> 0.0175
B37: 9.1 SLA de soporte | C37: 0.5 | D37: =C3*C31*C36*C37 -> 0.01 | E37: Compromiso contractual de tiempos máximos de respuesta y resolución según la severidad del incidente, con penalidades definidas ante incumplimientos. | F37: Un SLA de soporte sin penalidades es una declaración de intención, no un compromiso real — la exigibilidad contractual es lo que le da valor operativo. | G37: El SLA de soporte protege a Inversora de Capilla ante demoras inaceptables en resolución de incidentes — es la garantía formal de calidad del servicio post-venta. | H37: 1 | I37: =H37*C37 -> 0.5 | J37: =I37*D36 -> 0.01 | K37: 0.75 | L37: =K37*C37 -> 0.375 | M37: =L37*D36 -> 0.0075
B38: 9.2 Mesa de ayuda | C38: 0.5 | D38: =C3*C31*C36*C38 -> 0.01 | E38: Sistema formal de ticketing para la gestión de incidentes y consultas técnicas, con trazabilidad, priorización y escalamiento definidos y documentados. | F38: Una mesa de ayuda estructurada permite dar seguimiento formal a los problemas reportados y exigir su resolución dentro de los SLA establecidos. | G38: El ticketing formal es el mecanismo de accountability del soporte — sin él, los incidentes pueden perderse o resolverse de forma informal e inconsistente. | H38: 1 | I38: =H38*C38 -> 0.5 | J38: =I38*D36 -> 0.01 | K38: 1 | L38: =K38*C38 -> 0.5 | M38: =L38*D36 -> 0.01
B39: E. Innovación | C39: 0.1 | D39: =C3*C39 -> 0.02 | I39: =SUM(I40+I44)*C39 -> 0.099995 | J39: =SUM(J40+J44) -> 0.019999 | L39: =SUM(L40+L44)*C39 -> 0.08332875 | M39: =SUM(M40+M44) -> 0.01666575
B40: 10. Producto | C40: 0.5 | D40: =C3*C39*C40 -> 0.01 | I40: =SUM(I41:I43)*C40 -> 0.49995 | J40: =SUM(J41:J43) -> 0.009999 | L40: =SUM(L41:L43)*C40 -> 0.4582875 | M40: =SUM(M41:M43) -> 0.00916575
B41: 10.1 Roadmap público | C41: 0.3333 | D41: =C3*C39*C40*C41 -> 0.003333 | E41: Publicación del plan de evolución del producto con funcionalidades previstas, fechas orientativas y mecanismo para que clientes propongan y voten mejoras. | F41: Un roadmap público indica que el proveedor tiene visión de producto a largo plazo y está dispuesto a ser evaluado por sus compromisos de evolución. | G41: El roadmap permite evaluar si la dirección del producto es alineada con las necesidades futuras de Inversora de Capilla — reduce el riesgo de plataforma estancada. | H41: 1 | I41: =H41*C41 -> 0.3333 | J41: =I41*D40 -> 0.003333 | K41: 1 | L41: =K41*C41 -> 0.3333 | M41: =L41*D40 -> 0.003333
B42: 10.2 Frecuencia de releases | C42: 0.3333 | D42: =C3*C39*C40*C42 -> 0.003333 | E42: Cadencia de lanzamiento de nuevas versiones, correcciones y mejoras de la plataforma — indicador de la inversión activa del proveedor en el desarrollo del producto. | F42: Un proveedor con releases frecuentes demuestra inversión activa en I+D — el software que no se actualiza regularmente se vuelve obsoleto frente al mercado. | G42: La frecuencia de releases es un indicador de vitalidad del producto — plataformas con actualizaciones frecuentes ofrecen mayor protección de la inversión. | H42: 1 | I42: =H42*C42 -> 0.3333 | J42: =I42*D40 -> 0.003333 | K42: 1 | L42: =K42*C42 -> 0.3333 | M42: =L42*D40 -> 0.003333
B43: 10.3 Nuevas funcionalidades | C43: 0.3333 | D43: =C3*C39*C40*C43 -> 0.003333 | E43: Historial y calidad de las funcionalidades lanzadas en los últimos 12-24 meses, evaluando su relevancia para los casos de uso de Inversora de Capilla. | F43: El análisis de funcionalidades recientes permite inferir si el proveedor invierte en áreas relevantes para el sector inmobiliario y el mercado latinoamericano. | G43: Las funcionalidades lanzadas recientemente son evidencia concreta de la dirección estratégica del producto — más confiable que las declaraciones del roadmap. | H43: 1 | I43: =H43*C43 -> 0.3333 | J43: =I43*D40 -> 0.003333 | K43: 0.75 | L43: =K43*C43 -> 0.249975 | M43: =L43*D40 -> 0.00249975
B44: 11. IA | C44: 0.5 | D44: =C3*C39*C44 -> 0.01 | I44: =SUM(I45:I46)*C44 -> 0.5 | J44: =SUM(J45:J46) -> 0.01 | L44: =SUM(L45:L46)*C44 -> 0.375 | M44: =SUM(M45:M46) -> 0.0075
B45: 11.1 Capacidades IA nativas | C45: 0.5 | D45: =C3*C39*C44*C45 -> 0.005 | E45: Funcionalidades de inteligencia artificial integradas nativamente: scoring predictivo, procesamiento de lenguaje natural, generación de contenido o análisis automático. | F45: La IA nativa puede mejorar la eficiencia del equipo de ventas (lead scoring automático) y reducir el tiempo dedicado a tareas repetitivas de análisis. | G45: La IA integrada en el CRM es el diferenciador tecnológico más relevante para 2026 — los proveedores que la ofrecen nativamente posicionan mejor a sus clientes. | H45: 1 | I45: =H45*C45 -> 0.5 | J45: =I45*D44 -> 0.005 | K45: 0.75 | L45: =K45*C45 -> 0.375 | M45: =L45*D44 -> 0.00375
B46: 11.2 Automatización inteligente | C46: 0.5 | D46: =C3*C39*C44*C46 -> 0.005 | E46: Capacidad de la plataforma de aprender de los patrones de uso y proponer o ejecutar automatizaciones basadas en comportamiento histórico sin programación explícita. | F46: La automatización inteligente puede identificar patrones de comportamiento de clientes y sugerir acciones comerciales que el equipo no detectaría manualmente. | G46: La automatización inteligente multiplica la capacidad operativa sin agregar personal — diferenciador de productividad crítico para una empresa con recursos limitados. | H46: 1 | I46: =H46*C46 -> 0.5 | J46: =I46*D44 -> 0.005 | K46: 0.75 | L46: =K46*C46 -> 0.375 | M46: =L46*D44 -> 0.00375
B47: TOTAL | C47: =C4+C15+C23+C31+C39 -> 1 | D47: =D4+D15+D23+D31+D39 -> 0.2 | I47: =I4+I15+I23+I31+I39 -> 0.96133611 | J47: =J4+J15+J23+J31+J39 -> 0.19226722 | L47: =L4+L15+L23+L31+L39 -> 0.86689743 | M47: =M4+M15+M23+M31+M39 -> 0.17337949
B51: Categoría | C51: Peso
B52: Experiencia | C52: 0.3
B53: Solidez Empresarial | C53: 0.25
B54: Soporte | C54: 0.2
B55: Ecosistema | C55: 0.15
B56: Innovación | C56: 0.1
B59: Experiencia en la Industria
B60: (Aplica a experiencia inmobiliaria, construcción, PyMEs similares)
B61: Cumplimiento | C61: Criterio
B62: 1 | C62: Más de 10 casos comprobables en la industria o segmento
B63: 0.75 | C63: Entre 5 y 10 casos
B64: 0.5 | C64: Entre 2 y 4 casos
B65: 0.25 | C65: 1 caso documentado
B66: 0 | C66: Sin referencias relevantes
B68: Trayectoria y Solidez del Proveedor
B69: (Aplica a antigüedad, clientes, presencia internacional, estabilidad financiera)
B70: Cumplimiento | C70: Criterio
B71: 1 | C71: >15 años en el mercado y presencia internacional consolidada
B72: 0.75 | C72: 10-15 años y presencia regional
B73: 0.5 | C73: 5-10 años y presencia nacional
B74: 0.25 | C74: <5 años o presencia limitada
B75: 0 | C75: Sin evidencia suficiente
B77: Soporte y Servicio
B78: (Aplica a soporte en español, SLA, canales de atención)
B79: Cumplimiento | C79: Criterio
B80: 1 | C80: Soporte en español, múltiples canales, SLA formal 24x7
B81: 0.75 | C81: Soporte en español con SLA en horario extendido
B82: 0.5 | C82: Soporte en español sin SLA formal
B83: 0.25 | C83: Soporte principalmente en inglés
B84: 0 | C84: Sin soporte verificable
B86: Referencias y Satisfacción de Clientes
B87: (Aplica a casos de éxito, testimonios, reputación)
B88: Cumplimiento | C88: Criterio
B89: 1 | C89: Referencias verificables y alta satisfacción documentada
B90: 0.75 | C90: Varias referencias positivas
B91: 0.5 | C91: Algunas referencias positivas
B92: 0.25 | C92: Pocas referencias disponibles
B93: 0 | C93: Sin referencias
B95: Capacitación y Adopción
B96: (Aplica a onboarding, formación, documentación)
B97: Cumplimiento | C97: Criterio
B98: 1 | C98: Capacitación estructurada + documentación + academia
B99: 0.75 | C99: Capacitación y documentación formal
B100: 0.5 | C100: Documentación suficiente
B101: 0.25 | C101: Documentación básica
B102: 0 | C102: Sin recursos disponibles
B104: Certificaciones y Compliance
B105: (Aquí movería ISO 27001 según pidió el profesor)
B106: Cumplimiento | C106: Criterio
B107: 1 | C107: ISO 27001 + SOC 2 + cumplimiento normativo relevante
B108: 0.75 | C108: ISO 27001 o equivalente
B109: 0.5 | C109: Certificaciones parciales documentadas
B110: 0.25 | C110: Buenas prácticas declaradas sin certificación
B111: 0 | C111: Sin evidencia

Sheet Opinion Ejecutiva
A1: Conclusiones Estratégicas
A3: 1. La recomendación metodológica es correcta y madura para un proyecto PyME 2026.
A4: 2. El mayor riesgo no es tecnológico sino organizacional y cultural.
A5: 3. Dynamics 365 presenta sobre-engineering para una empresa de 5-15 usuarios.
A6: 4. Zoho CRM y proveedores PropTech argentinos ofrecen mejor relación costo-adopción.
A7: 5. La solidez del partner local será prioritaria para los socios por ausencia de IT interno.
A8: 6. El CAPEX inicial importará, pero la continuidad operativa y soporte pesarán más.
A9: 7. Se recomienda transición gradual y no apagón digital inmediato.

Sheet Gráfico Ponderación
D2: MS Dynamics 365 | E2: Zoho One | F2: Máximo
C3: FUNCIONAL | D3: ='Matriz Funcional'!J60 -> 0.41428125 | E3: ='Matriz Funcional'!M60 -> 0.41731875 | F3: 0.45
C4: TÉCNICO | D4: ='Matriz Técnica'!J60 -> 0.14607571 | E4: ='Matriz Técnica'!M60 -> 0.13452288 | F4: 0.15
C5: ECONÓMICO | D5: ='Matriz Económica'!J35 -> 0.127662 | E5: ='Matriz Económica'!M35 -> 0.179827 | F5: 0.2
C6: PROVEEDOR | D6: ='Matriz Proveedores'!J47 -> 0.19226722 | E6: ='Matriz Proveedores'!M47 -> 0.17337949 | F6: 0.2
D8: =SUM(D3:D6) -> 0.88028618 | E8: =SUM(E3:E6) -> 0.90504811
